Workbook
Name AOV: Analysis!$D$22
Name quantity: Analysis!$B$22
Name revenue: Analysis!$A$22

Sheet Dataset
A1: OrderID | B1: Date | C1: CustomerID | D1: Product | E1: Quantity | F1: UnitPrice | G1: ShippingAddress | H1: PaymentMethod | I1: OrderStatus | J1: TrackingNumber | K1: ItemsInCart | L1: CouponCode | M1: ReferralSource | N1: TotalPrice
A2: ORD200000 | B2: 44930 | C2: C72649 | D2: Monitor | E2: 5 | F2: 570.62 | G2: 928 Main St | H2: Debit Card | I2: Shipped | J2: TRK37947903 | K2: 7 | L2: SAVE10 | M2: Instagram | N2: 2853.1
A3: ORD200001 | B3: 45527 | C3: C75739 | D3: Phone | E3: 2 | F3: 151.35 | G3: 823 Main St | H3: Online | I3: Shipped | J3: TRK91186779 | K3: 3 | L3: SAVE10 | M3: Referral | N3: 302.7
A4: ORD200002 | B4: 45349 | C4: C81728 | D4: Tablet | E4: 5 | F4: 550.68 | G4: 512 Main St | H4: Credit Card | I4: Cancelled | J4: TRK42903982 | K4: 8 | L4: FREESHIP | M4: Email | N4: 2753.4
A5: ORD200003 | B5: 45214 | C5: C33540 | D5: Chair | E5: 1 | F5: 273.19 | G5: 275 Main St | H5: Debit Card | I5: Returned | J5: TRK62788070 | K5: 5 | L5: SAVE10 | M5: Facebook | N5: 273.19
A6: ORD200004 | B6: 45785 | C6: C81840 | D6: Printer | E6: 4 | F6: 626.01 | G6: 668 Main St | H6: Online | I6: Delivered | J6: TRK29241424 | K6: 8 | L6: SAVE10 | M6: Email | N6: 2504.04
A7: ORD200005 | B7: 45222 | C7: C37249 | D7: Phone | E7: 2 | F7: 245.86 | G7: 934 Main St | H7: Credit Card | I7: Shipped | J7: TRK72976927 | K7: 4 | L7: SAVE10 | M7: Instagram | N7: 491.72
A8: ORD200006 | B8: 45825 | C8: C83492 | D8: Laptop | E8: 1 | F8: 664.42 | G8: 986 Main St | H8: Gift Card | I8: Returned | J8: TRK96417362 | K8: 6 | L8: SAVE10 | M8: Facebook | N8: 664.42
A9: ORD200007 | B9: 45058 | C9: C41460 | D9: Monitor | E9: 5 | F9: 149.55 | G9: 706 Main St | H9: Cash | I9: Shipped | J9: TRK78809193 | K9: 9 | L9: FREESHIP | M9: Facebook | N9: 747.75
A10: ORD200008 | B10: 45749 | C10: C26817 | D10: Phone | E10: 2 | F10: 134.28 | G10: 904 Main St | H10: Gift Card | I10: Cancelled | J10: TRK61042692 | K10: 2 | M10: Email | N10: 268.56
A11: ORD200009 | B11: 45251 | C11: C31946 | D11: Desk | E11: 4 | F11: 509.38 | G11: 102 Main St | H11: Credit Card | I11: Shipped | J11: TRK33478363 | K11: 6 | L11: SAVE10 | M11: Google | N11: 2037.52
A12: ORD200010 | B12: 45289 | C12: C43443 | D12: Tablet | E12: 5 | F12: 625.97 | G12: 333 Main St | H12: Credit Card | I12: Returned | J12: TRK98859248 | K12: 9 | L12: WINTER15 | M12: Instagram | N12: 3129.85
A13: ORD200011 | B13: 45339 | C13: C93861 | D13: Monitor | E13: 3 | F13: 49.14 | G13: 831 Main St | H13: Online | I13: Returned | J13: TRK48234646 | K13: 7 | L13: SAVE10 | M13: Email | N13: 147.42
A14: ORD200012 | B14: 45580 | C14: C38785 | D14: Monitor | E14: 2 | F14: 180.5 | G14: 179 Main St | H14: Debit Card | I14: Pending | J14: TRK20419991 | K14: 6 | L14: FREESHIP | M14: Referral | N14: 361
A15: ORD200013 | B15: 45168 | C15: C88348 | D15: Laptop | E15: 3 | F15: 201.49 | G15: 903 Main St | H15: Credit Card | I15: Returned | J15: TRK81913874 | K15: 4 | L15: FREESHIP | M15: Facebook | N15: 604.47
A16: ORD200014 | B16: 45012 | C16: C98474 | D16: Tablet | E16: 2 | F16: 393.33 | G16: 980 Main St | H16: Debit Card | I16: Pending | J16: TRK79186539 | K16: 3 | L16: SAVE10 | M16: Instagram | N16: 786.66
A17: ORD200015 | B17: 45124 | C17: C39416 | D17: Printer | E17: 1 | F17: 473.96 | G17: 942 Main St | H17: Cash | I17: Delivered | J17: TRK54930938 | K17: 3 | M17: Google | N17: 473.96
A18: ORD200016 | B18: 44950 | C18: C28976 | D18: Printer | E18: 2 | F18: 533.81 | G18: 914 Main St | H18: Credit Card | I18: Pending | J18: TRK13194259 | K18: 3 | L18: FREESHIP | M18: Email | N18: 1067.62
A19: ORD200017 | B19: 45353 | C19: C60672 | D19: Tablet | E19: 1 | F19: 423.4 | G19: 382 Main St | H19: Debit Card | I19: Shipped | J19: TRK11972116 | K19: 3 | M19: Referral | N19: 423.4
A20: ORD200018 | B20: 45742 | C20: C84329 | D20: Desk | E20: 1 | F20: 431.44 | G20: 891 Main St | H20: Gift Card | I20: Pending | J20: TRK65191045 | K20: 3 | L20: SAVE10 | M20: Facebook | N20: 431.44
A21: ORD200019 | B21: 44949 | C21: C14552 | D21: Monitor | E21: 5 | F21: 224 | G21: 273 Main St | H21: Cash | I21: Returned | J21: TRK59101365 | K21: 9 | L21: SAVE10 | M21: Google | N21: 1120
A22: ORD200020 | B22: 45054 | C22: C54829 | D22: Chair | E22: 5 | F22: 62.51 | G22: 587 Main St | H22: Cash | I22: Pending | J22: TRK16718651 | K22: 9 | L22: WINTER15 | M22: Instagram | N22: 312.55
A23: ORD200021 | B23: 45613 | C23: C99023 | D23: Monitor | E23: 4 | F23: 342.95 | G23: 569 Main St | H23: Cash | I23: Delivered | J23: TRK52646983 | K23: 6 | M23: Google | N23: 1371.8
A24: ORD200022 | B24: 44955 | C24: C34416 | D24: Monitor | E24: 2 | F24: 49.62 | G24: 633 Main St | H24: Online | I24: Pending | J24: TRK75937350 | K24: 2 | L24: SAVE10 | M24: Google | N24: 99.24
A25: ORD200023 | B25: 45756 | C25: C42372 | D25: Phone | E25: 4 | F25: 273.25 | G25: 755 Main St | H25: Debit Card | I25: Cancelled | J25: TRK36168083 | K25: 5 | L25: FREESHIP | M25: Referral | N25: 1093
A26: ORD200024 | B26: 45595 | C26: C17470 | D26: Laptop | E26: 2 | F26: 230.95 | G26: 956 Main St | H26: Online | I26: Delivered | J26: TRK28775057 | K26: 3 | L26: WINTER15 | M26: Referral | N26: 461.9
A27: ORD200025 | B27: 45497 | C27: C42577 | D27: Monitor | E27: 1 | F27: 399.98 | G27: 709 Main St | H27: Debit Card | I27: Delivered | J27: TRK69423327 | K27: 3 | L27: WINTER15 | M27: Email | N27: 399.98
A28: ORD200026 | B28: 45357 | C28: C21944 | D28: Laptop | E28: 5 | F28: 59.55 | G28: 296 Main St | H28: Online | I28: Delivered | J28: TRK80276812 | K28: 6 | M28: Referral | N28: 297.75
A29: ORD200027 | B29: 45344 | C29: C97593 | D29: Printer | E29: 1 | F29: 472.74 | G29: 881 Main St | H29: Online | I29: Shipped | J29: TRK89117573 | K29: 6 | L29: WINTER15 | M29: Google | N29: 472.74
A30: ORD200028 | B30: 45251 | C30: C59823 | D30: Phone | E30: 4 | F30: 160.07 | G30: 568 Main St | H30: Online | I30: Pending | J30: TRK65895539 | K30: 5 | M30: Email | N30: 640.28
A31: ORD200029 | B31: 45555 | C31: C33260 | D31: Desk | E31: 3 | F31: 423.53 | G31: 930 Main St | H31: Credit Card | I31: Delivered | J31: TRK59744090 | K31: 6 | L31: SAVE10 | M31: Referral | N31: 1270.59
A32: ORD200030 | B32: 45738 | C32: C44267 | D32: Monitor | E32: 2 | F32: 426.7 | G32: 895 Main St | H32: Online | I32: Pending | J32: TRK54751444 | K32: 5 | L32: SAVE10 | M32: Referral | N32: 853.4
A33: ORD200031 | B33: 45107 | C33: C26445 | D33: Chair | E33: 3 | F33: 500.08 | G33: 996 Main St | H33: Debit Card | I33: Returned | J33: TRK31229981 | K33: 6 | M33: Facebook | N33: 1500.24
A34: ORD200032 | B34: 45047 | C34: C12388 | D34: Tablet | E34: 5 | F34: 536.72 | G34: 830 Main St | H34: Cash | I34: Delivered | J34: TRK99261395 | K34: 10 | M34: Email | N34: 2683.6
A35: ORD200033 | B35: 45082 | C35: C52184 | D35: Chair | E35: 1 | F35: 162.77 | G35: 912 Main St | H35: Online | I35: Cancelled | J35: TRK73312471 | K35: 4 | L35: WINTER15 | M35: Facebook | N35: 162.77
A36: ORD200034 | B36: 44933 | C36: C67195 | D36: Chair | E36: 4 | F36: 576.52 | G36: 926 Main St | H36: Credit Card | I36: Pending | J36: TRK55467915 | K36: 5 | L36: WINTER15 | M36: Facebook | N36: 2306.08
A37: ORD200035 | B37: 45633 | C37: C50304 | D37: Monitor | E37: 2 | F37: 465.15 | G37: 128 Main St | H37: Online | I37: Shipped | J37: TRK46850888 | K37: 2 | L37: SAVE10 | M37: Facebook | N37: 930.3
A38: ORD200036 | B38: 45785 | C38: C59337 | D38: Laptop | E38: 2 | F38: 534.43 | G38: 465 Main St | H38: Debit Card | I38: Pending | J38: TRK50961250 | K38: 5 | M38: Facebook | N38: 1068.86
A39: ORD200037 | B39: 45579 | C39: C10054 | D39: Laptop | E39: 2 | F39: 76.74 | G39: 409 Main St | H39: Cash | I39: Returned | J39: TRK94005261 | K39: 7 | L39: SAVE10 | M39: Instagram | N39: 153.48
A40: ORD200038 | B40: 45645 | C40: C15924 | D40: Laptop | E40: 1 | F40: 245.89 | G40: 549 Main St | H40: Debit Card | I40: Delivered | J40: TRK14835975 | K40: 3 | L40: SAVE10 | M40: Google | N40: 245.89
A41: ORD200039 | B41: 45715 | C41: C96664 | D41: Printer | E41: 3 | F41: 256.46 | G41: 666 Main St | H41: Credit Card | I41: Delivered | J41: TRK85508960 | K41: 4 | L41: SAVE10 | M41: Referral | N41: 769.38
A42: ORD200040 | B42: 45158 | C42: C84766 | D42: Desk | E42: 2 | F42: 344.02 | G42: 267 Main St | H42: Online | I42: Delivered | J42: TRK78967923 | K42: 4 | L42: FREESHIP | M42: Instagram | N42: 688.04
A43: ORD200041 | B43: 45265 | C43: C20212 | D43: Monitor | E43: 3 | F43: 611.45 | G43: 657 Main St | H43: Gift Card | I43: Pending | J43: TRK69733327 | K43: 4 | L43: FREESHIP | M43: Instagram | N43: 1834.35
A44: ORD200042 | B44: 45418 | C44: C28712 | D44: Printer | E44: 2 | F44: 151.66 | G44: 980 Main St | H44: Cash | I44: Cancelled | J44: TRK40772558 | K44: 6 | M44: Instagram | N44: 303.32
A45: ORD200043 | B45: 45274 | C45: C60572 | D45: Chair | E45: 3 | F45: 499.21 | G45: 871 Main St | H45: Online | I45: Cancelled | J45: TRK20351666 | K45: 8 | M45: Instagram | N45: 1497.63
A46: ORD200044 | B46: 45768 | C46: C73225 | D46: Phone | E46: 2 | F46: 550.18 | G46: 996 Main St | H46: Gift Card | I46: Returned | J46: TRK73848522 | K46: 3 | L46: FREESHIP | M46: Referral | N46: 1100.36
A47: ORD200045 | B47: 45332 | C47: C17388 | D47: Chair | E47: 1 | F47: 317.25 | G47: 157 Main St | H47: Debit Card | I47: Returned | J47: TRK47077395 | K47: 1 | L47: SAVE10 | M47: Facebook | N47: 317.25
A48: ORD200046 | B48: 45469 | C48: C43212 | D48: Monitor | E48: 4 | F48: 550.14 | G48: 223 Main St | H48: Debit Card | I48: Pending | J48: TRK25100762 | K48: 4 | L48: FREESHIP | M48: Instagram | N48: 2200.56
A49: ORD200047 | B49: 45126 | C49: C38134 | D49: Desk | E49: 2 | F49: 209.94 | G49: 323 Main St | H49: Credit Card | I49: Returned | J49: TRK42450754 | K49: 3 | L49: FREESHIP | M49: Email | N49: 419.88
A50: ORD200048 | B50: 45164 | C50: C12408 | D50: Monitor | E50: 2 | F50: 80.77 | G50: 464 Main St | H50: Debit Card | I50: Shipped | J50: TRK38938858 | K50: 4 | M50: Google | N50: 161.54
A51: ORD200049 | B51: 45206 | C51: C11985 | D51: Printer | E51: 1 | F51: 30.44 | G51: 633 Main St | H51: Credit Card | I51: Shipped | J51: TRK53272402 | K51: 1 | L51: SAVE10 | M51: Email | N51: 30.44
A52: ORD200050 | B52: 45138 | C52: C96494 | D52: Tablet | E52: 1 | F52: 179.22 | G52: 446 Main St | H52: Online | I52: Cancelled | J52: TRK14675049 | K52: 6 | L52: FREESHIP | M52: Instagram | N52: 179.22
A53: ORD200051 | B53: 45656 | C53: C36778 | D53: Tablet | E53: 1 | F53: 388.33 | G53: 434 Main St | H53: Cash | I53: Returned | J53: TRK67610289 | K53: 2 | L53: SAVE10 | M53: Facebook | N53: 388.33
A54: ORD200052 | B54: 45543 | C54: C30513 | D54: Tablet | E54: 1 | F54: 586.44 | G54: 232 Main St | H54: Online | I54: Returned | J54: TRK64320429 | K54: 5 | L54: SAVE10 | M54: Facebook | N54: 586.44
A55: ORD200053 | B55: 45430 | C55: C67551 | D55: Phone | E55: 4 | F55: 488.78 | G55: 512 Main St | H55: Online | I55: Returned | J55: TRK94992552 | K55: 5 | L55: FREESHIP | M55: Google | N55: 1955.12
A56: ORD200054 | B56: 45743 | C56: C48120 | D56: Chair | E56: 1 | F56: 280.25 | G56: 623 Main St | H56: Online | I56: Pending | J56: TRK11014449 | K56: 5 | L56: WINTER15 | M56: Email | N56: 280.25
A57: ORD200055 | B57: 45832 | C57: C95984 | D57: Printer | E57: 3 | F57: 344.4 | G57: 565 Main St | H57: Online | I57: Cancelled | J57: TRK67434829 | K57: 3 | M57: Facebook | N57: 1033.2
A58: ORD200056 | B58: 45067 | C58: C54298 | D58: Tablet | E58: 3 | F58: 479.21 | G58: 566 Main St | H58: Cash | I58: Cancelled | J58: TRK62902341 | K58: 5 | L58: WINTER15 | M58: Referral | N58: 1437.63
A59: ORD200057 | B59: 44948 | C59: C88036 | D59: Printer | E59: 5 | F59: 314.27 | G59: 842 Main St | H59: Cash | I59: Returned | J59: TRK52470128 | K59: 6 | L59: SAVE10 | M59: Instagram | N59: 1571.35
A60: ORD200058 | B60: 44941 | C60: C60190 | D60: Phone | E60: 4 | F60: 474.69 | G60: 202 Main St | H60: Gift Card | I60: Cancelled | J60: TRK70857868 | K60: 6 | L60: SAVE10 | M60: Google | N60: 1898.76
A61: ORD200059 | B61: 45546 | C61: C97603 | D61: Chair | E61: 4 | F61: 593.27 | G61: 811 Main St | H61: Online | I61: Shipped | J61: TRK47055028 | K61: 5 | M61: Facebook | N61: 2373.08
A62: ORD200060 | B62: 45525 | C62: C39256 | D62: Desk | E62: 1 | F62: 417.1 | G62: 634 Main St | H62: Debit Card | I62: Returned | J62: TRK23412025 | K62: 3 | L62: FREESHIP | M62: Referral | N62: 417.1
A63: ORD200061 | B63: 45375 | C63: C61618 | D63: Desk | E63: 4 | F63: 122.2 | G63: 104 Main St | H63: Cash | I63: Delivered | J63: TRK43458485 | K63: 7 | L63: FREESHIP | M63: Facebook | N63: 488.8
A64: ORD200062 | B64: 45160 | C64: C36497 | D64: Desk | E64: 2 | F64: 43.15 | G64: 691 Main St | H64: Debit Card | I64: Pending | J64: TRK12102911 | K64: 3 | L64: WINTER15 | M64: Email | N64: 86.3
A65: ORD200063 | B65: 45690 | C65: C96695 | D65: Chair | E65: 1 | F65: 564.86 | G65: 813 Main St | H65: Debit Card | I65: Shipped | J65: TRK64283851 | K65: 6 | L65: WINTER15 | M65: Referral | N65: 564.86
A66: ORD200064 | B66: 45833 | C66: C49720 | D66: Printer | E66: 3 | F66: 130.61 | G66: 752 Main St | H66: Debit Card | I66: Cancelled | J66: TRK55785217 | K66: 4 | L66: FREESHIP | M66: Facebook | N66: 391.83
A67: ORD200065 | B67: 45290 | C67: C97735 | D67: Monitor | E67: 5 | F67: 81.7 | G67: 385 Main St | H67: Credit Card | I67: Delivered | J67: TRK13743703 | K67: 6 | M67: Instagram | N67: 408.5
A68: ORD200066 | B68: 45611 | C68: C18104 | D68: Chair | E68: 5 | F68: 127.18 | G68: 715 Main St | H68: Cash | I68: Cancelled | J68: TRK15488568 | K68: 9 | L68: SAVE10 | M68: Referral | N68: 635.9
A69: ORD200067 | B69: 45635 | C69: C25587 | D69: Printer | E69: 4 | F69: 12.1 | G69: 440 Main St | H69: Debit Card | I69: Cancelled | J69: TRK55105323 | K69: 8 | M69: Google | N69: 48.4
A70: ORD200068 | B70: 45271 | C70: C41598 | D70: Chair | E70: 3 | F70: 490.92 | G70: 709 Main St | H70: Credit Card | I70: Pending | J70: TRK81665940 | K70: 5 | L70: FREESHIP | M70: Email | N70: 1472.76
A71: ORD200069 | B71: 45057 | C71: C43338 | D71: Monitor | E71: 3 | F71: 478.65 | G71: 552 Main St | H71: Online | I71: Shipped | J71: TRK35241775 | K71: 4 | M71: Referral | N71: 1435.95
A72: ORD200070 | B72: 45072 | C72: C25123 | D72: Desk | E72: 1 | F72: 629.21 | G72: 384 Main St | H72: Gift Card | I72: Pending | J72: TRK27812282 | K72: 2 | L72: FREESHIP | M72: Instagram | N72: 629.21
A73: ORD200071 | B73: 45818 | C73: C37454 | D73: Monitor | E73: 3 | F73: 434.45 | G73: 923 Main St | H73: Credit Card | I73: Pending | J73: TRK28252730 | K73: 4 | M73: Referral | N73: 1303.35
A74: ORD200072 | B74: 45648 | C74: C19451 | D74: Tablet | E74: 4 | F74: 589.44 | G74: 942 Main St | H74: Gift Card | I74: Returned | J74: TRK87787793 | K74: 5 | M74: Facebook | N74: 2357.76
A75: ORD200073 | B75: 45049 | C75: C17269 | D75: Monitor | E75: 4 | F75: 433.45 | G75: 129 Main St | H75: Gift Card | I75: Cancelled | J75: TRK79608389 | K75: 4 | M75: Facebook | N75: 1733.8
A76: ORD200074 | B76: 45101 | C76: C25382 | D76: Phone | E76: 5 | F76: 90.87 | G76: 622 Main St | H76: Cash | I76: Pending | J76: TRK64691287 | K76: 5 | M76: Instagram | N76: 454.35
A77: ORD200075 | B77: 45195 | C77: C80651 | D77: Tablet | E77: 3 | F77: 398.17 | G77: 917 Main St | H77: Debit Card | I77: Delivered | J77: TRK14846720 | K77: 5 | L77: SAVE10 | M77: Email | N77: 1194.51
A78: ORD200076 | B78: 45382 | C78: C58638 | D78: Laptop | E78: 4 | F78: 382.88 | G78: 239 Main St | H78: Cash | I78: Cancelled | J78: TRK38224871 | K78: 6 | L78: WINTER15 | M78: Email | N78: 1531.52
A79: ORD200077 | B79: 45436 | C79: C50121 | D79: Phone | E79: 1 | F79: 583.18 | G79: 348 Main St | H79: Credit Card | I79: Returned | J79: TRK79810059 | K79: 5 | M79: Google | N79: 583.18
A80: ORD200078 | B80: 45510 | C80: C32029 | D80: Printer | E80: 4 | F80: 175.36 | G80: 146 Main St | H80: Debit Card | I80: Delivered | J80: TRK68535532 | K80: 4 | L80: FREESHIP | M80: Instagram | N80: 701.44
A81: ORD200079 | B81: 45726 | C81: C76700 | D81: Tablet | E81: 2 | F81: 311.91 | G81: 103 Main St | H81: Online | I81: Shipped | J81: TRK13036341 | K81: 2 | M81: Facebook | N81: 623.82
A82: ORD200080 | B82: 45104 | C82: C29041 | D82: Phone | E82: 3 | F82: 589.56 | G82: 591 Main St | H82: Online | I82: Returned | J82: TRK28840655 | K82: 6 | M82: Facebook | N82: 1768.68
A83: ORD200081 | B83: 45085 | C83: C29314 | D83: Monitor | E83: 2 | F83: 394.3 | G83: 496 Main St | H83: Cash | I83: Shipped | J83: TRK59876213 | K83: 6 | L83: FREESHIP | M83: Email | N83: 788.6
A84: ORD200082 | B84: 45296 | C84: C65799 | D84: Tablet | E84: 4 | F84: 565.2 | G84: 971 Main St | H84: Debit Card | I84: Shipped | J84: TRK66906607 | K84: 9 | L84: SAVE10 | M84: Google | N84: 2260.8
A85: ORD200083 | B85: 45160 | C85: C15681 | D85: Laptop | E85: 4 | F85: 540.41 | G85: 989 Main St | H85: Credit Card | I85: Cancelled | J85: TRK75112172 | K85: 6 | M85: Referral | N85: 2161.64
A86: ORD200084 | B86: 45166 | C86: C64160 | D86: Monitor | E86: 2 | F86: 165.49 | G86: 967 Main St | H86: Online | I86: Shipped | J86: TRK34121529 | K86: 4 | L86: WINTER15 | M86: Instagram | N86: 330.98
A87: ORD200085 | B87: 45544 | C87: C14553 | D87: Tablet | E87: 3 | F87: 146.73 | G87: 768 Main St | H87: Cash | I87: Delivered | J87: TRK93538334 | K87: 8 | L87: FREESHIP | M87: Email | N87: 440.19
A88: ORD200086 | B88: 45462 | C88: C88205 | D88: Printer | E88: 5 | F88: 643.03 | G88: 447 Main St | H88: Online | I88: Cancelled | J88: TRK93504166 | K88: 5 | L88: FREESHIP | M88: Referral | N88: 3215.15
A89: ORD200087 | B89: 45575 | C89: C91245 | D89: Tablet | E89: 3 | F89: 225.11 | G89: 915 Main St | H89: Cash | I89: Shipped | J89: TRK46976391 | K89: 4 | L89: SAVE10 | M89: Facebook | N89: 675.33
A90: ORD200088 | B90: 45813 | C90: C75439 | D90: Desk | E90: 3 | F90: 114.81 | G90: 318 Main St | H90: Gift Card | I90: Cancelled | J90: TRK19831653 | K90: 7 | M90: Google | N90: 344.43
A91: ORD200089 | B91: 45713 | C91: C17181 | D91: Printer | E91: 5 | F91: 455.33 | G91: 291 Main St | H91: Credit Card | I91: Cancelled | J91: TRK78912978 | K91: 8 | L91: FREESHIP | M91: Google | N91: 2276.65
A92: ORD200090 | B92: 45187 | C92: C36540 | D92: Chair | E92: 4 | F92: 182.08 | G92: 611 Main St | H92: Gift Card | I92: Delivered | J92: TRK35828122 | K92: 4 | L92: SAVE10 | M92: Email | N92: 728.32
A93: ORD200091 | B93: 45000 | C93: C98216 | D93: Laptop | E93: 5 | F93: 492.75 | G93: 196 Main St | H93: Cash | I93: Shipped | J93: TRK40986666 | K93: 6 | L93: WINTER15 | M93: Referral | N93: 2463.75
A94: ORD200092 | B94: 45453 | C94: C29568 | D94: Printer | E94: 4 | F94: 48.61 | G94: 203 Main St | H94: Online | I94: Shipped | J94: TRK46531075 | K94: 7 | L94: FREESHIP | M94: Facebook | N94: 194.44
A95: ORD200093 | B95: 44940 | C95: C97262 | D95: Desk | E95: 4 | F95: 431.01 | G95: 837 Main St | H95: Credit Card | I95: Returned | J95: TRK65990229 | K95: 7 | M95: Referral | N95: 1724.04
A96: ORD200094 | B96: 44968 | C96: C79821 | D96: Chair | E96: 1 | F96: 531.18 | G96: 781 Main St | H96: Gift Card | I96: Returned | J96: TRK12780193 | K96: 6 | L96: WINTER15 | M96: Instagram | N96: 531.18
A97: ORD200095 | B97: 45009 | C97: C76761 | D97: Printer | E97: 4 | F97: 117.51 | G97: 839 Main St | H97: Debit Card | I97: Returned | J97: TRK60179774 | K97: 7 | M97: Referral | N97: 470.04
A98: ORD200096 | B98: 45444 | C98: C93007 | D98: Phone | E98: 2 | F98: 232.83 | G98: 103 Main St | H98: Gift Card | I98: Delivered | J98: TRK85696091 | K98: 7 | M98: Instagram | N98: 465.66
A99: ORD200097 | B99: 45678 | C99: C15624 | D99: Tablet | E99: 5 | F99: 619.52 | G99: 922 Main St | H99: Debit Card | I99: Pending | J99: TRK40621141 | K99: 9 | M99: Email | N99: 3097.6
A100: ORD200098 | B100: 44940 | C100: C70921 | D100: Printer | E100: 2 | F100: 228.54 | G100: 533 Main St | H100: Debit Card | I100: Pending | J100: TRK54983109 | K100: 3 | M100: Email | N100: 457.08
...

Sheet clean_data
A1: OrderID | B1: Date | C1: CustomerID | D1: Product | E1: Quantity | F1: UnitPrice | G1: ShippingAddress | H1: PaymentMethod | I1: OrderStatus | J1: TrackingNumber | K1: ItemsInCart | L1: CouponCode | M1: ReferralSource | N1: TotalPrice
A2: =TRIM(Dataset!A2) -> ORD200000 | B2: =Dataset!B2 -> 44930 | C2: =TRIM(Dataset!C2) -> C72649 | D2: =TRIM(Dataset!D2) -> Monitor | E2: =VALUE(TRIM(Dataset!E2)) -> 5 | F2: =VALUE(TRIM(Dataset!F2)) -> 570.62 | G2: =TRIM(Dataset!G2) -> 928 Main St | H2: =TRIM(Dataset!H2) -> Debit Card | I2: =TRIM(Dataset!I2) -> Shipped | J2: =TRIM(Dataset!J2) -> TRK37947903 | K2: =TRIM(Dataset!K2) -> 7 | L2: =Dataset!L2 -> SAVE10 | M2: =TRIM(Dataset!M2) -> Instagram | N2: =VALUE(TRIM(Dataset!N2)) -> 2853.1
A3: =TRIM(Dataset!A3) -> ORD200001 | B3: =Dataset!B3 -> 45527 | C3: =TRIM(Dataset!C3) -> C75739 | D3: =TRIM(Dataset!D3) -> Phone | E3: =VALUE(TRIM(Dataset!E3)) -> 2 | F3: =VALUE(TRIM(Dataset!F3)) -> 151.35 | G3: =TRIM(Dataset!G3) -> 823 Main St | H3: =TRIM(Dataset!H3) -> Online | I3: =TRIM(Dataset!I3) -> Shipped | J3: =TRIM(Dataset!J3) -> TRK91186779 | K3: =TRIM(Dataset!K3) -> 3 | L3: =Dataset!L3 -> SAVE10 | M3: =TRIM(Dataset!M3) -> Referral | N3: =VALUE(TRIM(Dataset!N3)) -> 302.7
A4: =TRIM(Dataset!A4) -> ORD200002 | B4: =Dataset!B4 -> 45349 | C4: =TRIM(Dataset!C4) -> C81728 | D4: =TRIM(Dataset!D4) -> Tablet | E4: =VALUE(TRIM(Dataset!E4)) -> 5 | F4: =VALUE(TRIM(Dataset!F4)) -> 550.68 | G4: =TRIM(Dataset!G4) -> 512 Main St | H4: =TRIM(Dataset!H4) -> Credit Card | I4: =TRIM(Dataset!I4) -> Cancelled | J4: =TRIM(Dataset!J4) -> TRK42903982 | K4: =TRIM(Dataset!K4) -> 8 | L4: =Dataset!L4 -> FREESHIP | M4: =TRIM(Dataset!M4) -> Email | N4: =VALUE(TRIM(Dataset!N4)) -> 2753.4
A5: =TRIM(Dataset!A5) -> ORD200003 | B5: =Dataset!B5 -> 45214 | C5: =TRIM(Dataset!C5) -> C33540 | D5: =TRIM(Dataset!D5) -> Chair | E5: =VALUE(TRIM(Dataset!E5)) -> 1 | F5: =VALUE(TRIM(Dataset!F5)) -> 273.19 | G5: =TRIM(Dataset!G5) -> 275 Main St | H5: =TRIM(Dataset!H5) -> Debit Card | I5: =TRIM(Dataset!I5) -> Returned | J5: =TRIM(Dataset!J5) -> TRK62788070 | K5: =TRIM(Dataset!K5) -> 5 | L5: =Dataset!L5 -> SAVE10 | M5: =TRIM(Dataset!M5) -> Facebook | N5: =VALUE(TRIM(Dataset!N5)) -> 273.19
A6: =TRIM(Dataset!A6) -> ORD200004 | B6: =Dataset!B6 -> 45785 | C6: =TRIM(Dataset!C6) -> C81840 | D6: =TRIM(Dataset!D6) -> Printer | E6: =VALUE(TRIM(Dataset!E6)) -> 4 | F6: =VALUE(TRIM(Dataset!F6)) -> 626.01 | G6: =TRIM(Dataset!G6) -> 668 Main St | H6: =TRIM(Dataset!H6) -> Online | I6: =TRIM(Dataset!I6) -> Delivered | J6: =TRIM(Dataset!J6) -> TRK29241424 | K6: =TRIM(Dataset!K6) -> 8 | L6: =Dataset!L6 -> SAVE10 | M6: =TRIM(Dataset!M6) -> Email | N6: =VALUE(TRIM(Dataset!N6)) -> 2504.04
A7: =TRIM(Dataset!A7) -> ORD200005 | B7: =Dataset!B7 -> 45222 | C7: =TRIM(Dataset!C7) -> C37249 | D7: =TRIM(Dataset!D7) -> Phone | E7: =VALUE(TRIM(Dataset!E7)) -> 2 | F7: =VALUE(TRIM(Dataset!F7)) -> 245.86 | G7: =TRIM(Dataset!G7) -> 934 Main St | H7: =TRIM(Dataset!H7) -> Credit Card | I7: =TRIM(Dataset!I7) -> Shipped | J7: =TRIM(Dataset!J7) -> TRK72976927 | K7: =TRIM(Dataset!K7) -> 4 | L7: =Dataset!L7 -> SAVE10 | M7: =TRIM(Dataset!M7) -> Instagram | N7: =VALUE(TRIM(Dataset!N7)) -> 491.72
A8: =TRIM(Dataset!A8) -> ORD200006 | B8: =Dataset!B8 -> 45825 | C8: =TRIM(Dataset!C8) -> C83492 | D8: =TRIM(Dataset!D8) -> Laptop | E8: =VALUE(TRIM(Dataset!E8)) -> 1 | F8: =VALUE(TRIM(Dataset!F8)) -> 664.42 | G8: =TRIM(Dataset!G8) -> 986 Main St | H8: =TRIM(Dataset!H8) -> Gift Card | I8: =TRIM(Dataset!I8) -> Returned | J8: =TRIM(Dataset!J8) -> TRK96417362 | K8: =TRIM(Dataset!K8) -> 6 | L8: =Dataset!L8 -> SAVE10 | M8: =TRIM(Dataset!M8) -> Facebook | N8: =VALUE(TRIM(Dataset!N8)) -> 664.42
A9: =TRIM(Dataset!A9) -> ORD200007 | B9: =Dataset!B9 -> 45058 | C9: =TRIM(Dataset!C9) -> C41460 | D9: =TRIM(Dataset!D9) -> Monitor | E9: =VALUE(TRIM(Dataset!E9)) -> 5 | F9: =VALUE(TRIM(Dataset!F9)) -> 149.55 | G9: =TRIM(Dataset!G9) -> 706 Main St | H9: =TRIM(Dataset!H9) -> Cash | I9: =TRIM(Dataset!I9) -> Shipped | J9: =TRIM(Dataset!J9) -> TRK78809193 | K9: =TRIM(Dataset!K9) -> 9 | L9: =Dataset!L9 -> FREESHIP | M9: =TRIM(Dataset!M9) -> Facebook | N9: =VALUE(TRIM(Dataset!N9)) -> 747.75
A10: =TRIM(Dataset!A10) -> ORD200008 | B10: =Dataset!B10 -> 45749 | C10: =TRIM(Dataset!C10) -> C26817 | D10: =TRIM(Dataset!D10) -> Phone | E10: =VALUE(TRIM(Dataset!E10)) -> 2 | F10: =VALUE(TRIM(Dataset!F10)) -> 134.28 | G10: =TRIM(Dataset!G10) -> 904 Main St | H10: =TRIM(Dataset!H10) -> Gift Card | I10: =TRIM(Dataset!I10) -> Cancelled | J10: =TRIM(Dataset!J10) -> TRK61042692 | K10: =TRIM(Dataset!K10) -> 2 | L10: NO COUPON | M10: =TRIM(Dataset!M10) -> Email | N10: =VALUE(TRIM(Dataset!N10)) -> 268.56
A11: =TRIM(Dataset!A11) -> ORD200009 | B11: =Dataset!B11 -> 45251 | C11: =TRIM(Dataset!C11) -> C31946 | D11: =TRIM(Dataset!D11) -> Desk | E11: =VALUE(TRIM(Dataset!E11)) -> 4 | F11: =VALUE(TRIM(Dataset!F11)) -> 509.38 | G11: =TRIM(Dataset!G11) -> 102 Main St | H11: =TRIM(Dataset!H11) -> Credit Card | I11: =TRIM(Dataset!I11) -> Shipped | J11: =TRIM(Dataset!J11) -> TRK33478363 | K11: =TRIM(Dataset!K11) -> 6 | L11: =Dataset!L11 -> SAVE10 | M11: =TRIM(Dataset!M11) -> Google | N11: =VALUE(TRIM(Dataset!N11)) -> 2037.52
A12: =TRIM(Dataset!A12) -> ORD200010 | B12: =Dataset!B12 -> 45289 | C12: =TRIM(Dataset!C12) -> C43443 | D12: =TRIM(Dataset!D12) -> Tablet | E12: =VALUE(TRIM(Dataset!E12)) -> 5 | F12: =VALUE(TRIM(Dataset!F12)) -> 625.97 | G12: =TRIM(Dataset!G12) -> 333 Main St | H12: =TRIM(Dataset!H12) -> Credit Card | I12: =TRIM(Dataset!I12) -> Returned | J12: =TRIM(Dataset!J12) -> TRK98859248 | K12: =TRIM(Dataset!K12) -> 9 | L12: =Dataset!L12 -> WINTER15 | M12: =TRIM(Dataset!M12) -> Instagram | N12: =VALUE(TRIM(Dataset!N12)) -> 3129.85
A13: =TRIM(Dataset!A13) -> ORD200011 | B13: =Dataset!B13 -> 45339 | C13: =TRIM(Dataset!C13) -> C93861 | D13: =TRIM(Dataset!D13) -> Monitor | E13: =VALUE(TRIM(Dataset!E13)) -> 3 | F13: =VALUE(TRIM(Dataset!F13)) -> 49.14 | G13: =TRIM(Dataset!G13) -> 831 Main St | H13: =TRIM(Dataset!H13) -> Online | I13: =TRIM(Dataset!I13) -> Returned | J13: =TRIM(Dataset!J13) -> TRK48234646 | K13: =TRIM(Dataset!K13) -> 7 | L13: =Dataset!L13 -> SAVE10 | M13: =TRIM(Dataset!M13) -> Email | N13: =VALUE(TRIM(Dataset!N13)) -> 147.42
A14: =TRIM(Dataset!A14) -> ORD200012 | B14: =Dataset!B14 -> 45580 | C14: =TRIM(Dataset!C14) -> C38785 | D14: =TRIM(Dataset!D14) -> Monitor | E14: =VALUE(TRIM(Dataset!E14)) -> 2 | F14: =VALUE(TRIM(Dataset!F14)) -> 180.5 | G14: =TRIM(Dataset!G14) -> 179 Main St | H14: =TRIM(Dataset!H14) -> Debit Card | I14: =TRIM(Dataset!I14) -> Pending | J14: =TRIM(Dataset!J14) -> TRK20419991 | K14: =TRIM(Dataset!K14) -> 6 | L14: =Dataset!L14 -> FREESHIP | M14: =TRIM(Dataset!M14) -> Referral | N14: =VALUE(TRIM(Dataset!N14)) -> 361
A15: =TRIM(Dataset!A15) -> ORD200013 | B15: =Dataset!B15 -> 45168 | C15: =TRIM(Dataset!C15) -> C88348 | D15: =TRIM(Dataset!D15) -> Laptop | E15: =VALUE(TRIM(Dataset!E15)) -> 3 | F15: =VALUE(TRIM(Dataset!F15)) -> 201.49 | G15: =TRIM(Dataset!G15) -> 903 Main St | H15: =TRIM(Dataset!H15) -> Credit Card | I15: =TRIM(Dataset!I15) -> Returned | J15: =TRIM(Dataset!J15) -> TRK81913874 | K15: =TRIM(Dataset!K15) -> 4 | L15: =Dataset!L15 -> FREESHIP | M15: =TRIM(Dataset!M15) -> Facebook | N15: =VALUE(TRIM(Dataset!N15)) -> 604.47
A16: =TRIM(Dataset!A16) -> ORD200014 | B16: =Dataset!B16 -> 45012 | C16: =TRIM(Dataset!C16) -> C98474 | D16: =TRIM(Dataset!D16) -> Tablet | E16: =VALUE(TRIM(Dataset!E16)) -> 2 | F16: =VALUE(TRIM(Dataset!F16)) -> 393.33 | G16: =TRIM(Dataset!G16) -> 980 Main St | H16: =TRIM(Dataset!H16) -> Debit Card | I16: =TRIM(Dataset!I16) -> Pending | J16: =TRIM(Dataset!J16) -> TRK79186539 | K16: =TRIM(Dataset!K16) -> 3 | L16: =Dataset!L16 -> SAVE10 | M16: =TRIM(Dataset!M16) -> Instagram | N16: =VALUE(TRIM(Dataset!N16)) -> 786.66
A17: =TRIM(Dataset!A17) -> ORD200015 | B17: =Dataset!B17 -> 45124 | C17: =TRIM(Dataset!C17) -> C39416 | D17: =TRIM(Dataset!D17) -> Printer | E17: =VALUE(TRIM(Dataset!E17)) -> 1 | F17: =VALUE(TRIM(Dataset!F17)) -> 473.96 | G17: =TRIM(Dataset!G17) -> 942 Main St | H17: =TRIM(Dataset!H17) -> Cash | I17: =TRIM(Dataset!I17) -> Delivered | J17: =TRIM(Dataset!J17) -> TRK54930938 | K17: =TRIM(Dataset!K17) -> 3 | L17: NO COUPON | M17: =TRIM(Dataset!M17) -> Google | N17: =VALUE(TRIM(Dataset!N17)) -> 473.96
A18: =TRIM(Dataset!A18) -> ORD200016 | B18: =Dataset!B18 -> 44950 | C18: =TRIM(Dataset!C18) -> C28976 | D18: =TRIM(Dataset!D18) -> Printer | E18: =VALUE(TRIM(Dataset!E18)) -> 2 | F18: =VALUE(TRIM(Dataset!F18)) -> 533.81 | G18: =TRIM(Dataset!G18) -> 914 Main St | H18: =TRIM(Dataset!H18) -> Credit Card | I18: =TRIM(Dataset!I18) -> Pending | J18: =TRIM(Dataset!J18) -> TRK13194259 | K18: =TRIM(Dataset!K18) -> 3 | L18: =Dataset!L18 -> FREESHIP | M18: =TRIM(Dataset!M18) -> Email | N18: =VALUE(TRIM(Dataset!N18)) -> 1067.62
A19: =TRIM(Dataset!A19) -> ORD200017 | B19: =Dataset!B19 -> 45353 | C19: =TRIM(Dataset!C19) -> C60672 | D19: =TRIM(Dataset!D19) -> Tablet | E19: =VALUE(TRIM(Dataset!E19)) -> 1 | F19: =VALUE(TRIM(Dataset!F19)) -> 423.4 | G19: =TRIM(Dataset!G19) -> 382 Main St | H19: =TRIM(Dataset!H19) -> Debit Card | I19: =TRIM(Dataset!I19) -> Shipped | J19: =TRIM(Dataset!J19) -> TRK11972116 | K19: =TRIM(Dataset!K19) -> 3 | L19: NO COUPON | M19: =TRIM(Dataset!M19) -> Referral | N19: =VALUE(TRIM(Dataset!N19)) -> 423.4
A20: =TRIM(Dataset!A20) -> ORD200018 | B20: =Dataset!B20 -> 45742 | C20: =TRIM(Dataset!C20) -> C84329 | D20: =TRIM(Dataset!D20) -> Desk | E20: =VALUE(TRIM(Dataset!E20)) -> 1 | F20: =VALUE(TRIM(Dataset!F20)) -> 431.44 | G20: =TRIM(Dataset!G20) -> 891 Main St | H20: =TRIM(Dataset!H20) -> Gift Card | I20: =TRIM(Dataset!I20) -> Pending | J20: =TRIM(Dataset!J20) -> TRK65191045 | K20: =TRIM(Dataset!K20) -> 3 | L20: =Dataset!L20 -> SAVE10 | M20: =TRIM(Dataset!M20) -> Facebook | N20: =VALUE(TRIM(Dataset!N20)) -> 431.44
A21: =TRIM(Dataset!A21) -> ORD200019 | B21: =Dataset!B21 -> 44949 | C21: =TRIM(Dataset!C21) -> C14552 | D21: =TRIM(Dataset!D21) -> Monitor | E21: =VALUE(TRIM(Dataset!E21)) -> 5 | F21: =VALUE(TRIM(Dataset!F21)) -> 224 | G21: =TRIM(Dataset!G21) -> 273 Main St | H21: =TRIM(Dataset!H21) -> Cash | I21: =TRIM(Dataset!I21) -> Returned | J21: =TRIM(Dataset!J21) -> TRK59101365 | K21: =TRIM(Dataset!K21) -> 9 | L21: =Dataset!L21 -> SAVE10 | M21: =TRIM(Dataset!M21) -> Google | N21: =VALUE(TRIM(Dataset!N21)) -> 1120
A22: =TRIM(Dataset!A22) -> ORD200020 | B22: =Dataset!B22 -> 45054 | C22: =TRIM(Dataset!C22) -> C54829 | D22: =TRIM(Dataset!D22) -> Chair | E22: =VALUE(TRIM(Dataset!E22)) -> 5 | F22: =VALUE(TRIM(Dataset!F22)) -> 62.51 | G22: =TRIM(Dataset!G22) -> 587 Main St | H22: =TRIM(Dataset!H22) -> Cash | I22: =TRIM(Dataset!I22) -> Pending | J22: =TRIM(Dataset!J22) -> TRK16718651 | K22: =TRIM(Dataset!K22) -> 9 | L22: =Dataset!L22 -> WINTER15 | M22: =TRIM(Dataset!M22) -> Instagram | N22: =VALUE(TRIM(Dataset!N22)) -> 312.55
A23: =TRIM(Dataset!A23) -> ORD200021 | B23: =Dataset!B23 -> 45613 | C23: =TRIM(Dataset!C23) -> C99023 | D23: =TRIM(Dataset!D23) -> Monitor | E23: =VALUE(TRIM(Dataset!E23)) -> 4 | F23: =VALUE(TRIM(Dataset!F23)) -> 342.95 | G23: =TRIM(Dataset!G23) -> 569 Main St | H23: =TRIM(Dataset!H23) -> Cash | I23: =TRIM(Dataset!I23) -> Delivered | J23: =TRIM(Dataset!J23) -> TRK52646983 | K23: =TRIM(Dataset!K23) -> 6 | L23: NO COUPON | M23: =TRIM(Dataset!M23) -> Google | N23: =VALUE(TRIM(Dataset!N23)) -> 1371.8
A24: =TRIM(Dataset!A24) -> ORD200022 | B24: =Dataset!B24 -> 44955 | C24: =TRIM(Dataset!C24) -> C34416 | D24: =TRIM(Dataset!D24) -> Monitor | E24: =VALUE(TRIM(Dataset!E24)) -> 2 | F24: =VALUE(TRIM(Dataset!F24)) -> 49.62 | G24: =TRIM(Dataset!G24) -> 633 Main St | H24: =TRIM(Dataset!H24) -> Online | I24: =TRIM(Dataset!I24) -> Pending | J24: =TRIM(Dataset!J24) -> TRK75937350 | K24: =TRIM(Dataset!K24) -> 2 | L24: =Dataset!L24 -> SAVE10 | M24: =TRIM(Dataset!M24) -> Google | N24: =VALUE(TRIM(Dataset!N24)) -> 99.24
A25: =TRIM(Dataset!A25) -> ORD200023 | B25: =Dataset!B25 -> 45756 | C25: =TRIM(Dataset!C25) -> C42372 | D25: =TRIM(Dataset!D25) -> Phone | E25: =VALUE(TRIM(Dataset!E25)) -> 4 | F25: =VALUE(TRIM(Dataset!F25)) -> 273.25 | G25: =TRIM(Dataset!G25) -> 755 Main St | H25: =TRIM(Dataset!H25) -> Debit Card | I25: =TRIM(Dataset!I25) -> Cancelled | J25: =TRIM(Dataset!J25) -> TRK36168083 | K25: =TRIM(Dataset!K25) -> 5 | L25: =Dataset!L25 -> FREESHIP | M25: =TRIM(Dataset!M25) -> Referral | N25: =VALUE(TRIM(Dataset!N25)) -> 1093
A26: =TRIM(Dataset!A26) -> ORD200024 | B26: =Dataset!B26 -> 45595 | C26: =TRIM(Dataset!C26) -> C17470 | D26: =TRIM(Dataset!D26) -> Laptop | E26: =VALUE(TRIM(Dataset!E26)) -> 2 | F26: =VALUE(TRIM(Dataset!F26)) -> 230.95 | G26: =TRIM(Dataset!G26) -> 956 Main St | H26: =TRIM(Dataset!H26) -> Online | I26: =TRIM(Dataset!I26) -> Delivered | J26: =TRIM(Dataset!J26) -> TRK28775057 | K26: =TRIM(Dataset!K26) -> 3 | L26: =Dataset!L26 -> WINTER15 | M26: =TRIM(Dataset!M26) -> Referral | N26: =VALUE(TRIM(Dataset!N26)) -> 461.9
A27: =TRIM(Dataset!A27) -> ORD200025 | B27: =Dataset!B27 -> 45497 | C27: =TRIM(Dataset!C27) -> C42577 | D27: =TRIM(Dataset!D27) -> Monitor | E27: =VALUE(TRIM(Dataset!E27)) -> 1 | F27: =VALUE(TRIM(Dataset!F27)) -> 399.98 | G27: =TRIM(Dataset!G27) -> 709 Main St | H27: =TRIM(Dataset!H27) -> Debit Card | I27: =TRIM(Dataset!I27) -> Delivered | J27: =TRIM(Dataset!J27) -> TRK69423327 | K27: =TRIM(Dataset!K27) -> 3 | L27: =Dataset!L27 -> WINTER15 | M27: =TRIM(Dataset!M27) -> Email | N27: =VALUE(TRIM(Dataset!N27)) -> 399.98
A28: =TRIM(Dataset!A28) -> ORD200026 | B28: =Dataset!B28 -> 45357 | C28: =TRIM(Dataset!C28) -> C21944 | D28: =TRIM(Dataset!D28) -> Laptop | E28: =VALUE(TRIM(Dataset!E28)) -> 5 | F28: =VALUE(TRIM(Dataset!F28)) -> 59.55 | G28: =TRIM(Dataset!G28) -> 296 Main St | H28: =TRIM(Dataset!H28) -> Online | I28: =TRIM(Dataset!I28) -> Delivered | J28: =TRIM(Dataset!J28) -> TRK80276812 | K28: =TRIM(Dataset!K28) -> 6 | L28: NO COUPON | M28: =TRIM(Dataset!M28) -> Referral | N28: =VALUE(TRIM(Dataset!N28)) -> 297.75
A29: =TRIM(Dataset!A29) -> ORD200027 | B29: =Dataset!B29 -> 45344 | C29: =TRIM(Dataset!C29) -> C97593 | D29: =TRIM(Dataset!D29) -> Printer | E29: =VALUE(TRIM(Dataset!E29)) -> 1 | F29: =VALUE(TRIM(Dataset!F29)) -> 472.74 | G29: =TRIM(Dataset!G29) -> 881 Main St | H29: =TRIM(Dataset!H29) -> Online | I29: =TRIM(Dataset!I29) -> Shipped | J29: =TRIM(Dataset!J29) -> TRK89117573 | K29: =TRIM(Dataset!K29) -> 6 | L29: =Dataset!L29 -> WINTER15 | M29: =TRIM(Dataset!M29) -> Google | N29: =VALUE(TRIM(Dataset!N29)) -> 472.74
A30: =TRIM(Dataset!A30) -> ORD200028 | B30: =Dataset!B30 -> 45251 | C30: =TRIM(Dataset!C30) -> C59823 | D30: =TRIM(Dataset!D30) -> Phone | E30: =VALUE(TRIM(Dataset!E30)) -> 4 | F30: =VALUE(TRIM(Dataset!F30)) -> 160.07 | G30: =TRIM(Dataset!G30) -> 568 Main St | H30: =TRIM(Dataset!H30) -> Online | I30: =TRIM(Dataset!I30) -> Pending | J30: =TRIM(Dataset!J30) -> TRK65895539 | K30: =TRIM(Dataset!K30) -> 5 | L30: NO COUPON | M30: =TRIM(Dataset!M30) -> Email | N30: =VALUE(TRIM(Dataset!N30)) -> 640.28
A31: =TRIM(Dataset!A31) -> ORD200029 | B31: =Dataset!B31 -> 45555 | C31: =TRIM(Dataset!C31) -> C33260 | D31: =TRIM(Dataset!D31) -> Desk | E31: =VALUE(TRIM(Dataset!E31)) -> 3 | F31: =VALUE(TRIM(Dataset!F31)) -> 423.53 | G31: =TRIM(Dataset!G31) -> 930 Main St | H31: =TRIM(Dataset!H31) -> Credit Card | I31: =TRIM(Dataset!I31) -> Delivered | J31: =TRIM(Dataset!J31) -> TRK59744090 | K31: =TRIM(Dataset!K31) -> 6 | L31: =Dataset!L31 -> SAVE10 | M31: =TRIM(Dataset!M31) -> Referral | N31: =VALUE(TRIM(Dataset!N31)) -> 1270.59
A32: =TRIM(Dataset!A32) -> ORD200030 | B32: =Dataset!B32 -> 45738 | C32: =TRIM(Dataset!C32) -> C44267 | D32: =TRIM(Dataset!D32) -> Monitor | E32: =VALUE(TRIM(Dataset!E32)) -> 2 | F32: =VALUE(TRIM(Dataset!F32)) -> 426.7 | G32: =TRIM(Dataset!G32) -> 895 Main St | H32: =TRIM(Dataset!H32) -> Online | I32: =TRIM(Dataset!I32) -> Pending | J32: =TRIM(Dataset!J32) -> TRK54751444 | K32: =TRIM(Dataset!K32) -> 5 | L32: =Dataset!L32 -> SAVE10 | M32: =TRIM(Dataset!M32) -> Referral | N32: =VALUE(TRIM(Dataset!N32)) -> 853.4
A33: =TRIM(Dataset!A33) -> ORD200031 | B33: =Dataset!B33 -> 45107 | C33: =TRIM(Dataset!C33) -> C26445 | D33: =TRIM(Dataset!D33) -> Chair | E33: =VALUE(TRIM(Dataset!E33)) -> 3 | F33: =VALUE(TRIM(Dataset!F33)) -> 500.08 | G33: =TRIM(Dataset!G33) -> 996 Main St | H33: =TRIM(Dataset!H33) -> Debit Card | I33: =TRIM(Dataset!I33) -> Returned | J33: =TRIM(Dataset!J33) -> TRK31229981 | K33: =TRIM(Dataset!K33) -> 6 | L33: NO COUPON | M33: =TRIM(Dataset!M33) -> Facebook | N33: =VALUE(TRIM(Dataset!N33)) -> 1500.24
A34: =TRIM(Dataset!A34) -> ORD200032 | B34: =Dataset!B34 -> 45047 | C34: =TRIM(Dataset!C34) -> C12388 | D34: =TRIM(Dataset!D34) -> Tablet | E34: =VALUE(TRIM(Dataset!E34)) -> 5 | F34: =VALUE(TRIM(Dataset!F34)) -> 536.72 | G34: =TRIM(Dataset!G34) -> 830 Main St | H34: =TRIM(Dataset!H34) -> Cash | I34: =TRIM(Dataset!I34) -> Delivered | J34: =TRIM(Dataset!J34) -> TRK99261395 | K34: =TRIM(Dataset!K34) -> 10 | L34: NO COUPON | M34: =TRIM(Dataset!M34) -> Email | N34: =VALUE(TRIM(Dataset!N34)) -> 2683.6
A35: =TRIM(Dataset!A35) -> ORD200033 | B35: =Dataset!B35 -> 45082 | C35: =TRIM(Dataset!C35) -> C52184 | D35: =TRIM(Dataset!D35) -> Chair | E35: =VALUE(TRIM(Dataset!E35)) -> 1 | F35: =VALUE(TRIM(Dataset!F35)) -> 162.77 | G35: =TRIM(Dataset!G35) -> 912 Main St | H35: =TRIM(Dataset!H35) -> Online | I35: =TRIM(Dataset!I35) -> Cancelled | J35: =TRIM(Dataset!J35) -> TRK73312471 | K35: =TRIM(Dataset!K35) -> 4 | L35: =Dataset!L35 -> WINTER15 | M35: =TRIM(Dataset!M35) -> Facebook | N35: =VALUE(TRIM(Dataset!N35)) -> 162.77
A36: =TRIM(Dataset!A36) -> ORD200034 | B36: =Dataset!B36 -> 44933 | C36: =TRIM(Dataset!C36) -> C67195 | D36: =TRIM(Dataset!D36) -> Chair | E36: =VALUE(TRIM(Dataset!E36)) -> 4 | F36: =VALUE(TRIM(Dataset!F36)) -> 576.52 | G36: =TRIM(Dataset!G36) -> 926 Main St | H36: =TRIM(Dataset!H36) -> Credit Card | I36: =TRIM(Dataset!I36) -> Pending | J36: =TRIM(Dataset!J36) -> TRK55467915 | K36: =TRIM(Dataset!K36) -> 5 | L36: =Dataset!L36 -> WINTER15 | M36: =TRIM(Dataset!M36) -> Facebook | N36: =VALUE(TRIM(Dataset!N36)) -> 2306.08
A37: =TRIM(Dataset!A37) -> ORD200035 | B37: =Dataset!B37 -> 45633 | C37: =TRIM(Dataset!C37) -> C50304 | D37: =TRIM(Dataset!D37) -> Monitor | E37: =VALUE(TRIM(Dataset!E37)) -> 2 | F37: =VALUE(TRIM(Dataset!F37)) -> 465.15 | G37: =TRIM(Dataset!G37) -> 128 Main St | H37: =TRIM(Dataset!H37) -> Online | I37: =TRIM(Dataset!I37) -> Shipped | J37: =TRIM(Dataset!J37) -> TRK46850888 | K37: =TRIM(Dataset!K37) -> 2 | L37: =Dataset!L37 -> SAVE10 | M37: =TRIM(Dataset!M37) -> Facebook | N37: =VALUE(TRIM(Dataset!N37)) -> 930.3
A38: =TRIM(Dataset!A38) -> ORD200036 | B38: =Dataset!B38 -> 45785 | C38: =TRIM(Dataset!C38) -> C59337 | D38: =TRIM(Dataset!D38) -> Laptop | E38: =VALUE(TRIM(Dataset!E38)) -> 2 | F38: =VALUE(TRIM(Dataset!F38)) -> 534.43 | G38: =TRIM(Dataset!G38) -> 465 Main St | H38: =TRIM(Dataset!H38) -> Debit Card | I38: =TRIM(Dataset!I38) -> Pending | J38: =TRIM(Dataset!J38) -> TRK50961250 | K38: =TRIM(Dataset!K38) -> 5 | L38: NO COUPON | M38: =TRIM(Dataset!M38) -> Facebook | N38: =VALUE(TRIM(Dataset!N38)) -> 1068.86
A39: =TRIM(Dataset!A39) -> ORD200037 | B39: =Dataset!B39 -> 45579 | C39: =TRIM(Dataset!C39) -> C10054 | D39: =TRIM(Dataset!D39) -> Laptop | E39: =VALUE(TRIM(Dataset!E39)) -> 2 | F39: =VALUE(TRIM(Dataset!F39)) -> 76.74 | G39: =TRIM(Dataset!G39) -> 409 Main St | H39: =TRIM(Dataset!H39) -> Cash | I39: =TRIM(Dataset!I39) -> Returned | J39: =TRIM(Dataset!J39) -> TRK94005261 | K39: =TRIM(Dataset!K39) -> 7 | L39: =Dataset!L39 -> SAVE10 | M39: =TRIM(Dataset!M39) -> Instagram | N39: =VALUE(TRIM(Dataset!N39)) -> 153.48
A40: =TRIM(Dataset!A40) -> ORD200038 | B40: =Dataset!B40 -> 45645 | C40: =TRIM(Dataset!C40) -> C15924 | D40: =TRIM(Dataset!D40) -> Laptop | E40: =VALUE(TRIM(Dataset!E40)) -> 1 | F40: =VALUE(TRIM(Dataset!F40)) -> 245.89 | G40: =TRIM(Dataset!G40) -> 549 Main St | H40: =TRIM(Dataset!H40) -> Debit Card | I40: =TRIM(Dataset!I40) -> Delivered | J40: =TRIM(Dataset!J40) -> TRK14835975 | K40: =TRIM(Dataset!K40) -> 3 | L40: =Dataset!L40 -> SAVE10 | M40: =TRIM(Dataset!M40) -> Google | N40: =VALUE(TRIM(Dataset!N40)) -> 245.89
A41: =TRIM(Dataset!A41) -> ORD200039 | B41: =Dataset!B41 -> 45715 | C41: =TRIM(Dataset!C41) -> C96664 | D41: =TRIM(Dataset!D41) -> Printer | E41: =VALUE(TRIM(Dataset!E41)) -> 3 | F41: =VALUE(TRIM(Dataset!F41)) -> 256.46 | G41: =TRIM(Dataset!G41) -> 666 Main St | H41: =TRIM(Dataset!H41) -> Credit Card | I41: =TRIM(Dataset!I41) -> Delivered | J41: =TRIM(Dataset!J41) -> TRK85508960 | K41: =TRIM(Dataset!K41) -> 4 | L41: =Dataset!L41 -> SAVE10 | M41: =TRIM(Dataset!M41) -> Referral | N41: =VALUE(TRIM(Dataset!N41)) -> 769.38
A42: =TRIM(Dataset!A42) -> ORD200040 | B42: =Dataset!B42 -> 45158 | C42: =TRIM(Dataset!C42) -> C84766 | D42: =TRIM(Dataset!D42) -> Desk | E42: =VALUE(TRIM(Dataset!E42)) -> 2 | F42: =VALUE(TRIM(Dataset!F42)) -> 344.02 | G42: =TRIM(Dataset!G42) -> 267 Main St | H42: =TRIM(Dataset!H42) -> Online | I42: =TRIM(Dataset!I42) -> Delivered | J42: =TRIM(Dataset!J42) -> TRK78967923 | K42: =TRIM(Dataset!K42) -> 4 | L42: =Dataset!L42 -> FREESHIP | M42: =TRIM(Dataset!M42) -> Instagram | N42: =VALUE(TRIM(Dataset!N42)) -> 688.04
A43: =TRIM(Dataset!A43) -> ORD200041 | B43: =Dataset!B43 -> 45265 | C43: =TRIM(Dataset!C43) -> C20212 | D43: =TRIM(Dataset!D43) -> Monitor | E43: =VALUE(TRIM(Dataset!E43)) -> 3 | F43: =VALUE(TRIM(Dataset!F43)) -> 611.45 | G43: =TRIM(Dataset!G43) -> 657 Main St | H43: =TRIM(Dataset!H43) -> Gift Card | I43: =TRIM(Dataset!I43) -> Pending | J43: =TRIM(Dataset!J43) -> TRK69733327 | K43: =TRIM(Dataset!K43) -> 4 | L43: =Dataset!L43 -> FREESHIP | M43: =TRIM(Dataset!M43) -> Instagram | N43: =VALUE(TRIM(Dataset!N43)) -> 1834.35
A44: =TRIM(Dataset!A44) -> ORD200042 | B44: =Dataset!B44 -> 45418 | C44: =TRIM(Dataset!C44) -> C28712 | D44: =TRIM(Dataset!D44) -> Printer | E44: =VALUE(TRIM(Dataset!E44)) -> 2 | F44: =VALUE(TRIM(Dataset!F44)) -> 151.66 | G44: =TRIM(Dataset!G44) -> 980 Main St | H44: =TRIM(Dataset!H44) -> Cash | I44: =TRIM(Dataset!I44) -> Cancelled | J44: =TRIM(Dataset!J44) -> TRK40772558 | K44: =TRIM(Dataset!K44) -> 6 | L44: NO COUPON | M44: =TRIM(Dataset!M44) -> Instagram | N44: =VALUE(TRIM(Dataset!N44)) -> 303.32
A45: =TRIM(Dataset!A45) -> ORD200043 | B45: =Dataset!B45 -> 45274 | C45: =TRIM(Dataset!C45) -> C60572 | D45: =TRIM(Dataset!D45) -> Chair | E45: =VALUE(TRIM(Dataset!E45)) -> 3 | F45: =VALUE(TRIM(Dataset!F45)) -> 499.21 | G45: =TRIM(Dataset!G45) -> 871 Main St | H45: =TRIM(Dataset!H45) -> Online | I45: =TRIM(Dataset!I45) -> Cancelled | J45: =TRIM(Dataset!J45) -> TRK20351666 | K45: =TRIM(Dataset!K45) -> 8 | L45: NO COUPON | M45: =TRIM(Dataset!M45) -> Instagram | N45: =VALUE(TRIM(Dataset!N45)) -> 1497.63
A46: =TRIM(Dataset!A46) -> ORD200044 | B46: =Dataset!B46 -> 45768 | C46: =TRIM(Dataset!C46) -> C73225 | D46: =TRIM(Dataset!D46) -> Phone | E46: =VALUE(TRIM(Dataset!E46)) -> 2 | F46: =VALUE(TRIM(Dataset!F46)) -> 550.18 | G46: =TRIM(Dataset!G46) -> 996 Main St | H46: =TRIM(Dataset!H46) -> Gift Card | I46: =TRIM(Dataset!I46) -> Returned | J46: =TRIM(Dataset!J46) -> TRK73848522 | K46: =TRIM(Dataset!K46) -> 3 | L46: =Dataset!L46 -> FREESHIP | M46: =TRIM(Dataset!M46) -> Referral | N46: =VALUE(TRIM(Dataset!N46)) -> 1100.36
A47: =TRIM(Dataset!A47) -> ORD200045 | B47: =Dataset!B47 -> 45332 | C47: =TRIM(Dataset!C47) -> C17388 | D47: =TRIM(Dataset!D47) -> Chair | E47: =VALUE(TRIM(Dataset!E47)) -> 1 | F47: =VALUE(TRIM(Dataset!F47)) -> 317.25 | G47: =TRIM(Dataset!G47) -> 157 Main St | H47: =TRIM(Dataset!H47) -> Debit Card | I47: =TRIM(Dataset!I47) -> Returned | J47: =TRIM(Dataset!J47) -> TRK47077395 | K47: =TRIM(Dataset!K47) -> 1 | L47: =Dataset!L47 -> SAVE10 | M47: =TRIM(Dataset!M47) -> Facebook | N47: =VALUE(TRIM(Dataset!N47)) -> 317.25
A48: =TRIM(Dataset!A48) -> ORD200046 | B48: =Dataset!B48 -> 45469 | C48: =TRIM(Dataset!C48) -> C43212 | D48: =TRIM(Dataset!D48) -> Monitor | E48: =VALUE(TRIM(Dataset!E48)) -> 4 | F48: =VALUE(TRIM(Dataset!F48)) -> 550.14 | G48: =TRIM(Dataset!G48) -> 223 Main St | H48: =TRIM(Dataset!H48) -> Debit Card | I48: =TRIM(Dataset!I48) -> Pending | J48: =TRIM(Dataset!J48) -> TRK25100762 | K48: =TRIM(Dataset!K48) -> 4 | L48: =Dataset!L48 -> FREESHIP | M48: =TRIM(Dataset!M48) -> Instagram | N48: =VALUE(TRIM(Dataset!N48)) -> 2200.56
A49: =TRIM(Dataset!A49) -> ORD200047 | B49: =Dataset!B49 -> 45126 | C49: =TRIM(Dataset!C49) -> C38134 | D49: =TRIM(Dataset!D49) -> Desk | E49: =VALUE(TRIM(Dataset!E49)) -> 2 | F49: =VALUE(TRIM(Dataset!F49)) -> 209.94 | G49: =TRIM(Dataset!G49) -> 323 Main St | H49: =TRIM(Dataset!H49) -> Credit Card | I49: =TRIM(Dataset!I49) -> Returned | J49: =TRIM(Dataset!J49) -> TRK42450754 | K49: =TRIM(Dataset!K49) -> 3 | L49: =Dataset!L49 -> FREESHIP | M49: =TRIM(Dataset!M49) -> Email | N49: =VALUE(TRIM(Dataset!N49)) -> 419.88
A50: =TRIM(Dataset!A50) -> ORD200048 | B50: =Dataset!B50 -> 45164 | C50: =TRIM(Dataset!C50) -> C12408 | D50: =TRIM(Dataset!D50) -> Monitor | E50: =VALUE(TRIM(Dataset!E50)) -> 2 | F50: =VALUE(TRIM(Dataset!F50)) -> 80.77 | G50: =TRIM(Dataset!G50) -> 464 Main St | H50: =TRIM(Dataset!H50) -> Debit Card | I50: =TRIM(Dataset!I50) -> Shipped | J50: =TRIM(Dataset!J50) -> TRK38938858 | K50: =TRIM(Dataset!K50) -> 4 | L50: NO COUPON | M50: =TRIM(Dataset!M50) -> Google | N50: =VALUE(TRIM(Dataset!N50)) -> 161.54
A51: =TRIM(Dataset!A51) -> ORD200049 | B51: =Dataset!B51 -> 45206 | C51: =TRIM(Dataset!C51) -> C11985 | D51: =TRIM(Dataset!D51) -> Printer | E51: =VALUE(TRIM(Dataset!E51)) -> 1 | F51: =VALUE(TRIM(Dataset!F51)) -> 30.44 | G51: =TRIM(Dataset!G51) -> 633 Main St | H51: =TRIM(Dataset!H51) -> Credit Card | I51: =TRIM(Dataset!I51) -> Shipped | J51: =TRIM(Dataset!J51) -> TRK53272402 | K51: =TRIM(Dataset!K51) -> 1 | L51: =Dataset!L51 -> SAVE10 | M51: =TRIM(Dataset!M51) -> Email | N51: =VALUE(TRIM(Dataset!N51)) -> 30.44
A52: =TRIM(Dataset!A52) -> ORD200050 | B52: =Dataset!B52 -> 45138 | C52: =TRIM(Dataset!C52) -> C96494 | D52: =TRIM(Dataset!D52) -> Tablet | E52: =VALUE(TRIM(Dataset!E52)) -> 1 | F52: =VALUE(TRIM(Dataset!F52)) -> 179.22 | G52: =TRIM(Dataset!G52) -> 446 Main St | H52: =TRIM(Dataset!H52) -> Online | I52: =TRIM(Dataset!I52) -> Cancelled | J52: =TRIM(Dataset!J52) -> TRK14675049 | K52: =TRIM(Dataset!K52) -> 6 | L52: =Dataset!L52 -> FREESHIP | M52: =TRIM(Dataset!M52) -> Instagram | N52: =VALUE(TRIM(Dataset!N52)) -> 179.22
A53: =TRIM(Dataset!A53) -> ORD200051 | B53: =Dataset!B53 -> 45656 | C53: =TRIM(Dataset!C53) -> C36778 | D53: =TRIM(Dataset!D53) -> Tablet | E53: =VALUE(TRIM(Dataset!E53)) -> 1 | F53: =VALUE(TRIM(Dataset!F53)) -> 388.33 | G53: =TRIM(Dataset!G53) -> 434 Main St | H53: =TRIM(Dataset!H53) -> Cash | I53: =TRIM(Dataset!I53) -> Returned | J53: =TRIM(Dataset!J53) -> TRK67610289 | K53: =TRIM(Dataset!K53) -> 2 | L53: =Dataset!L53 -> SAVE10 | M53: =TRIM(Dataset!M53) -> Facebook | N53: =VALUE(TRIM(Dataset!N53)) -> 388.33
A54: =TRIM(Dataset!A54) -> ORD200052 | B54: =Dataset!B54 -> 45543 | C54: =TRIM(Dataset!C54) -> C30513 | D54: =TRIM(Dataset!D54) -> Tablet | E54: =VALUE(TRIM(Dataset!E54)) -> 1 | F54: =VALUE(TRIM(Dataset!F54)) -> 586.44 | G54: =TRIM(Dataset!G54) -> 232 Main St | H54: =TRIM(Dataset!H54) -> Online | I54: =TRIM(Dataset!I54) -> Returned | J54: =TRIM(Dataset!J54) -> TRK64320429 | K54: =TRIM(Dataset!K54) -> 5 | L54: =Dataset!L54 -> SAVE10 | M54: =TRIM(Dataset!M54) -> Facebook | N54: =VALUE(TRIM(Dataset!N54)) -> 586.44
A55: =TRIM(Dataset!A55) -> ORD200053 | B55: =Dataset!B55 -> 45430 | C55: =TRIM(Dataset!C55) -> C67551 | D55: =TRIM(Dataset!D55) -> Phone | E55: =VALUE(TRIM(Dataset!E55)) -> 4 | F55: =VALUE(TRIM(Dataset!F55)) -> 488.78 | G55: =TRIM(Dataset!G55) -> 512 Main St | H55: =TRIM(Dataset!H55) -> Online | I55: =TRIM(Dataset!I55) -> Returned | J55: =TRIM(Dataset!J55) -> TRK94992552 | K55: =TRIM(Dataset!K55) -> 5 | L55: =Dataset!L55 -> FREESHIP | M55: =TRIM(Dataset!M55) -> Google | N55: =VALUE(TRIM(Dataset!N55)) -> 1955.12
A56: =TRIM(Dataset!A56) -> ORD200054 | B56: =Dataset!B56 -> 45743 | C56: =TRIM(Dataset!C56) -> C48120 | D56: =TRIM(Dataset!D56) -> Chair | E56: =VALUE(TRIM(Dataset!E56)) -> 1 | F56: =VALUE(TRIM(Dataset!F56)) -> 280.25 | G56: =TRIM(Dataset!G56) -> 623 Main St | H56: =TRIM(Dataset!H56) -> Online | I56: =TRIM(Dataset!I56) -> Pending | J56: =TRIM(Dataset!J56) -> TRK11014449 | K56: =TRIM(Dataset!K56) -> 5 | L56: =Dataset!L56 -> WINTER15 | M56: =TRIM(Dataset!M56) -> Email | N56: =VALUE(TRIM(Dataset!N56)) -> 280.25
A57: =TRIM(Dataset!A57) -> ORD200055 | B57: =Dataset!B57 -> 45832 | C57: =TRIM(Dataset!C57) -> C95984 | D57: =TRIM(Dataset!D57) -> Printer | E57: =VALUE(TRIM(Dataset!E57)) -> 3 | F57: =VALUE(TRIM(Dataset!F57)) -> 344.4 | G57: =TRIM(Dataset!G57) -> 565 Main St | H57: =TRIM(Dataset!H57) -> Online | I57: =TRIM(Dataset!I57) -> Cancelled | J57: =TRIM(Dataset!J57) -> TRK67434829 | K57: =TRIM(Dataset!K57) -> 3 | L57: NO COUPON | M57: =TRIM(Dataset!M57) -> Facebook | N57: =VALUE(TRIM(Dataset!N57)) -> 1033.2
A58: =TRIM(Dataset!A58) -> ORD200056 | B58: =Dataset!B58 -> 45067 | C58: =TRIM(Dataset!C58) -> C54298 | D58: =TRIM(Dataset!D58) -> Tablet | E58: =VALUE(TRIM(Dataset!E58)) -> 3 | F58: =VALUE(TRIM(Dataset!F58)) -> 479.21 | G58: =TRIM(Dataset!G58) -> 566 Main St | H58: =TRIM(Dataset!H58) -> Cash | I58: =TRIM(Dataset!I58) -> Cancelled | J58: =TRIM(Dataset!J58) -> TRK62902341 | K58: =TRIM(Dataset!K58) -> 5 | L58: =Dataset!L58 -> WINTER15 | M58: =TRIM(Dataset!M58) -> Referral | N58: =VALUE(TRIM(Dataset!N58)) -> 1437.63
A59: =TRIM(Dataset!A59) -> ORD200057 | B59: =Dataset!B59 -> 44948 | C59: =TRIM(Dataset!C59) -> C88036 | D59: =TRIM(Dataset!D59) -> Printer | E59: =VALUE(TRIM(Dataset!E59)) -> 5 | F59: =VALUE(TRIM(Dataset!F59)) -> 314.27 | G59: =TRIM(Dataset!G59) -> 842 Main St | H59: =TRIM(Dataset!H59) -> Cash | I59: =TRIM(Dataset!I59) -> Returned | J59: =TRIM(Dataset!J59) -> TRK52470128 | K59: =TRIM(Dataset!K59) -> 6 | L59: =Dataset!L59 -> SAVE10 | M59: =TRIM(Dataset!M59) -> Instagram | N59: =VALUE(TRIM(Dataset!N59)) -> 1571.35
A60: =TRIM(Dataset!A60) -> ORD200058 | B60: =Dataset!B60 -> 44941 | C60: =TRIM(Dataset!C60) -> C60190 | D60: =TRIM(Dataset!D60) -> Phone | E60: =VALUE(TRIM(Dataset!E60)) -> 4 | F60: =VALUE(TRIM(Dataset!F60)) -> 474.69 | G60: =TRIM(Dataset!G60) -> 202 Main St | H60: =TRIM(Dataset!H60) -> Gift Card | I60: =TRIM(Dataset!I60) -> Cancelled | J60: =TRIM(Dataset!J60) -> TRK70857868 | K60: =TRIM(Dataset!K60) -> 6 | L60: =Dataset!L60 -> SAVE10 | M60: =TRIM(Dataset!M60) -> Google | N60: =VALUE(TRIM(Dataset!N60)) -> 1898.76
A61: =TRIM(Dataset!A61) -> ORD200059 | B61: =Dataset!B61 -> 45546 | C61: =TRIM(Dataset!C61) -> C97603 | D61: =TRIM(Dataset!D61) -> Chair | E61: =VALUE(TRIM(Dataset!E61)) -> 4 | F61: =VALUE(TRIM(Dataset!F61)) -> 593.27 | G61: =TRIM(Dataset!G61) -> 811 Main St | H61: =TRIM(Dataset!H61) -> Online | I61: =TRIM(Dataset!I61) -> Shipped | J61: =TRIM(Dataset!J61) -> TRK47055028 | K61: =TRIM(Dataset!K61) -> 5 | L61: NO COUPON | M61: =TRIM(Dataset!M61) -> Facebook | N61: =VALUE(TRIM(Dataset!N61)) -> 2373.08
A62: =TRIM(Dataset!A62) -> ORD200060 | B62: =Dataset!B62 -> 45525 | C62: =TRIM(Dataset!C62) -> C39256 | D62: =TRIM(Dataset!D62) -> Desk | E62: =VALUE(TRIM(Dataset!E62)) -> 1 | F62: =VALUE(TRIM(Dataset!F62)) -> 417.1 | G62: =TRIM(Dataset!G62) -> 634 Main St | H62: =TRIM(Dataset!H62) -> Debit Card | I62: =TRIM(Dataset!I62) -> Returned | J62: =TRIM(Dataset!J62) -> TRK23412025 | K62: =TRIM(Dataset!K62) -> 3 | L62: =Dataset!L62 -> FREESHIP | M62: =TRIM(Dataset!M62) -> Referral | N62: =VALUE(TRIM(Dataset!N62)) -> 417.1
A63: =TRIM(Dataset!A63) -> ORD200061 | B63: =Dataset!B63 -> 45375 | C63: =TRIM(Dataset!C63) -> C61618 | D63: =TRIM(Dataset!D63) -> Desk | E63: =VALUE(TRIM(Dataset!E63)) -> 4 | F63: =VALUE(TRIM(Dataset!F63)) -> 122.2 | G63: =TRIM(Dataset!G63) -> 104 Main St | H63: =TRIM(Dataset!H63) -> Cash | I63: =TRIM(Dataset!I63) -> Delivered | J63: =TRIM(Dataset!J63) -> TRK43458485 | K63: =TRIM(Dataset!K63) -> 7 | L63: =Dataset!L63 -> FREESHIP | M63: =TRIM(Dataset!M63) -> Facebook | N63: =VALUE(TRIM(Dataset!N63)) -> 488.8
A64: =TRIM(Dataset!A64) -> ORD200062 | B64: =Dataset!B64 -> 45160 | C64: =TRIM(Dataset!C64) -> C36497 | D64: =TRIM(Dataset!D64) -> Desk | E64: =VALUE(TRIM(Dataset!E64)) -> 2 | F64: =VALUE(TRIM(Dataset!F64)) -> 43.15 | G64: =TRIM(Dataset!G64) -> 691 Main St | H64: =TRIM(Dataset!H64) -> Debit Card | I64: =TRIM(Dataset!I64) -> Pending | J64: =TRIM(Dataset!J64) -> TRK12102911 | K64: =TRIM(Dataset!K64) -> 3 | L64: =Dataset!L64 -> WINTER15 | M64: =TRIM(Dataset!M64) -> Email | N64: =VALUE(TRIM(Dataset!N64)) -> 86.3
A65: =TRIM(Dataset!A65) -> ORD200063 | B65: =Dataset!B65 -> 45690 | C65: =TRIM(Dataset!C65) -> C96695 | D65: =TRIM(Dataset!D65) -> Chair | E65: =VALUE(TRIM(Dataset!E65)) -> 1 | F65: =VALUE(TRIM(Dataset!F65)) -> 564.86 | G65: =TRIM(Dataset!G65) -> 813 Main St | H65: =TRIM(Dataset!H65) -> Debit Card | I65: =TRIM(Dataset!I65) -> Shipped | J65: =TRIM(Dataset!J65) -> TRK64283851 | K65: =TRIM(Dataset!K65) -> 6 | L65: =Dataset!L65 -> WINTER15 | M65: =TRIM(Dataset!M65) -> Referral | N65: =VALUE(TRIM(Dataset!N65)) -> 564.86
A66: =TRIM(Dataset!A66) -> ORD200064 | B66: =Dataset!B66 -> 45833 | C66: =TRIM(Dataset!C66) -> C49720 | D66: =TRIM(Dataset!D66) -> Printer | E66: =VALUE(TRIM(Dataset!E66)) -> 3 | F66: =VALUE(TRIM(Dataset!F66)) -> 130.61 | G66: =TRIM(Dataset!G66) -> 752 Main St | H66: =TRIM(Dataset!H66) -> Debit Card | I66: =TRIM(Dataset!I66) -> Cancelled | J66: =TRIM(Dataset!J66) -> TRK55785217 | K66: =TRIM(Dataset!K66) -> 4 | L66: =Dataset!L66 -> FREESHIP | M66: =TRIM(Dataset!M66) -> Facebook | N66: =VALUE(TRIM(Dataset!N66)) -> 391.83
A67: =TRIM(Dataset!A67) -> ORD200065 | B67: =Dataset!B67 -> 45290 | C67: =TRIM(Dataset!C67) -> C97735 | D67: =TRIM(Dataset!D67) -> Monitor | E67: =VALUE(TRIM(Dataset!E67)) -> 5 | F67: =VALUE(TRIM(Dataset!F67)) -> 81.7 | G67: =TRIM(Dataset!G67) -> 385 Main St | H67: =TRIM(Dataset!H67) -> Credit Card | I67: =TRIM(Dataset!I67) -> Delivered | J67: =TRIM(Dataset!J67) -> TRK13743703 | K67: =TRIM(Dataset!K67) -> 6 | L67: NO COUPON | M67: =TRIM(Dataset!M67) -> Instagram | N67: =VALUE(TRIM(Dataset!N67)) -> 408.5
A68: =TRIM(Dataset!A68) -> ORD200066 | B68: =Dataset!B68 -> 45611 | C68: =TRIM(Dataset!C68) -> C18104 | D68: =TRIM(Dataset!D68) -> Chair | E68: =VALUE(TRIM(Dataset!E68)) -> 5 | F68: =VALUE(TRIM(Dataset!F68)) -> 127.18 | G68: =TRIM(Dataset!G68) -> 715 Main St | H68: =TRIM(Dataset!H68) -> Cash | I68: =TRIM(Dataset!I68) -> Cancelled | J68: =TRIM(Dataset!J68) -> TRK15488568 | K68: =TRIM(Dataset!K68) -> 9 | L68: =Dataset!L68 -> SAVE10 | M68: =TRIM(Dataset!M68) -> Referral | N68: =VALUE(TRIM(Dataset!N68)) -> 635.9
A69: =TRIM(Dataset!A69) -> ORD200067 | B69: =Dataset!B69 -> 45635 | C69: =TRIM(Dataset!C69) -> C25587 | D69: =TRIM(Dataset!D69) -> Printer | E69: =VALUE(TRIM(Dataset!E69)) -> 4 | F69: =VALUE(TRIM(Dataset!F69)) -> 12.1 | G69: =TRIM(Dataset!G69) -> 440 Main St | H69: =TRIM(Dataset!H69) -> Debit Card | I69: =TRIM(Dataset!I69) -> Cancelled | J69: =TRIM(Dataset!J69) -> TRK55105323 | K69: =TRIM(Dataset!K69) -> 8 | L69: NO COUPON | M69: =TRIM(Dataset!M69) -> Google | N69: =VALUE(TRIM(Dataset!N69)) -> 48.4
A70: =TRIM(Dataset!A70) -> ORD200068 | B70: =Dataset!B70 -> 45271 | C70: =TRIM(Dataset!C70) -> C41598 | D70: =TRIM(Dataset!D70) -> Chair | E70: =VALUE(TRIM(Dataset!E70)) -> 3 | F70: =VALUE(TRIM(Dataset!F70)) -> 490.92 | G70: =TRIM(Dataset!G70) -> 709 Main St | H70: =TRIM(Dataset!H70) -> Credit Card | I70: =TRIM(Dataset!I70) -> Pending | J70: =TRIM(Dataset!J70) -> TRK81665940 | K70: =TRIM(Dataset!K70) -> 5 | L70: =Dataset!L70 -> FREESHIP | M70: =TRIM(Dataset!M70) -> Email | N70: =VALUE(TRIM(Dataset!N70)) -> 1472.76
A71: =TRIM(Dataset!A71) -> ORD200069 | B71: =Dataset!B71 -> 45057 | C71: =TRIM(Dataset!C71) -> C43338 | D71: =TRIM(Dataset!D71) -> Monitor | E71: =VALUE(TRIM(Dataset!E71)) -> 3 | F71: =VALUE(TRIM(Dataset!F71)) -> 478.65 | G71: =TRIM(Dataset!G71) -> 552 Main St | H71: =TRIM(Dataset!H71) -> Online | I71: =TRIM(Dataset!I71) -> Shipped | J71: =TRIM(Dataset!J71) -> TRK35241775 | K71: =TRIM(Dataset!K71) -> 4 | L71: NO COUPON | M71: =TRIM(Dataset!M71) -> Referral | N71: =VALUE(TRIM(Dataset!N71)) -> 1435.95
A72: =TRIM(Dataset!A72) -> ORD200070 | B72: =Dataset!B72 -> 45072 | C72: =TRIM(Dataset!C72) -> C25123 | D72: =TRIM(Dataset!D72) -> Desk | E72: =VALUE(TRIM(Dataset!E72)) -> 1 | F72: =VALUE(TRIM(Dataset!F72)) -> 629.21 | G72: =TRIM(Dataset!G72) -> 384 Main St | H72: =TRIM(Dataset!H72) -> Gift Card | I72: =TRIM(Dataset!I72) -> Pending | J72: =TRIM(Dataset!J72) -> TRK27812282 | K72: =TRIM(Dataset!K72) -> 2 | L72: =Dataset!L72 -> FREESHIP | M72: =TRIM(Dataset!M72) -> Instagram | N72: =VALUE(TRIM(Dataset!N72)) -> 629.21
A73: =TRIM(Dataset!A73) -> ORD200071 | B73: =Dataset!B73 -> 45818 | C73: =TRIM(Dataset!C73) -> C37454 | D73: =TRIM(Dataset!D73) -> Monitor | E73: =VALUE(TRIM(Dataset!E73)) -> 3 | F73: =VALUE(TRIM(Dataset!F73)) -> 434.45 | G73: =TRIM(Dataset!G73) -> 923 Main St | H73: =TRIM(Dataset!H73) -> Credit Card | I73: =TRIM(Dataset!I73) -> Pending | J73: =TRIM(Dataset!J73) -> TRK28252730 | K73: =TRIM(Dataset!K73) -> 4 | L73: NO COUPON | M73: =TRIM(Dataset!M73) -> Referral | N73: =VALUE(TRIM(Dataset!N73)) -> 1303.35
A74: =TRIM(Dataset!A74) -> ORD200072 | B74: =Dataset!B74 -> 45648 | C74: =TRIM(Dataset!C74) -> C19451 | D74: =TRIM(Dataset!D74) -> Tablet | E74: =VALUE(TRIM(Dataset!E74)) -> 4 | F74: =VALUE(TRIM(Dataset!F74)) -> 589.44 | G74: =TRIM(Dataset!G74) -> 942 Main St | H74: =TRIM(Dataset!H74) -> Gift Card | I74: =TRIM(Dataset!I74) -> Returned | J74: =TRIM(Dataset!J74) -> TRK87787793 | K74: =TRIM(Dataset!K74) -> 5 | L74: NO COUPON | M74: =TRIM(Dataset!M74) -> Facebook | N74: =VALUE(TRIM(Dataset!N74)) -> 2357.76
A75: =TRIM(Dataset!A75) -> ORD200073 | B75: =Dataset!B75 -> 45049 | C75: =TRIM(Dataset!C75) -> C17269 | D75: =TRIM(Dataset!D75) -> Monitor | E75: =VALUE(TRIM(Dataset!E75)) -> 4 | F75: =VALUE(TRIM(Dataset!F75)) -> 433.45 | G75: =TRIM(Dataset!G75) -> 129 Main St | H75: =TRIM(Dataset!H75) -> Gift Card | I75: =TRIM(Dataset!I75) -> Cancelled | J75: =TRIM(Dataset!J75) -> TRK79608389 | K75: =TRIM(Dataset!K75) -> 4 | L75: NO COUPON | M75: =TRIM(Dataset!M75) -> Facebook | N75: =VALUE(TRIM(Dataset!N75)) -> 1733.8
A76: =TRIM(Dataset!A76) -> ORD200074 | B76: =Dataset!B76 -> 45101 | C76: =TRIM(Dataset!C76) -> C25382 | D76: =TRIM(Dataset!D76) -> Phone | E76: =VALUE(TRIM(Dataset!E76)) -> 5 | F76: =VALUE(TRIM(Dataset!F76)) -> 90.87 | G76: =TRIM(Dataset!G76) -> 622 Main St | H76: =TRIM(Dataset!H76) -> Cash | I76: =TRIM(Dataset!I76) -> Pending | J76: =TRIM(Dataset!J76) -> TRK64691287 | K76: =TRIM(Dataset!K76) -> 5 | L76: NO COUPON | M76: =TRIM(Dataset!M76) -> Instagram | N76: =VALUE(TRIM(Dataset!N76)) -> 454.35
A77: =TRIM(Dataset!A77) -> ORD200075 | B77: =Dataset!B77 -> 45195 | C77: =TRIM(Dataset!C77) -> C80651 | D77: =TRIM(Dataset!D77) -> Tablet | E77: =VALUE(TRIM(Dataset!E77)) -> 3 | F77: =VALUE(TRIM(Dataset!F77)) -> 398.17 | G77: =TRIM(Dataset!G77) -> 917 Main St | H77: =TRIM(Dataset!H77) -> Debit Card | I77: =TRIM(Dataset!I77) -> Delivered | J77: =TRIM(Dataset!J77) -> TRK14846720 | K77: =TRIM(Dataset!K77) -> 5 | L77: =Dataset!L77 -> SAVE10 | M77: =TRIM(Dataset!M77) -> Email | N77: =VALUE(TRIM(Dataset!N77)) -> 1194.51
A78: =TRIM(Dataset!A78) -> ORD200076 | B78: =Dataset!B78 -> 45382 | C78: =TRIM(Dataset!C78) -> C58638 | D78: =TRIM(Dataset!D78) -> Laptop | E78: =VALUE(TRIM(Dataset!E78)) -> 4 | F78: =VALUE(TRIM(Dataset!F78)) -> 382.88 | G78: =TRIM(Dataset!G78) -> 239 Main St | H78: =TRIM(Dataset!H78) -> Cash | I78: =TRIM(Dataset!I78) -> Cancelled | J78: =TRIM(Dataset!J78) -> TRK38224871 | K78: =TRIM(Dataset!K78) -> 6 | L78: =Dataset!L78 -> WINTER15 | M78: =TRIM(Dataset!M78) -> Email | N78: =VALUE(TRIM(Dataset!N78)) -> 1531.52
A79: =TRIM(Dataset!A79) -> ORD200077 | B79: =Dataset!B79 -> 45436 | C79: =TRIM(Dataset!C79) -> C50121 | D79: =TRIM(Dataset!D79) -> Phone | E79: =VALUE(TRIM(Dataset!E79)) -> 1 | F79: =VALUE(TRIM(Dataset!F79)) -> 583.18 | G79: =TRIM(Dataset!G79) -> 348 Main St | H79: =TRIM(Dataset!H79) -> Credit Card | I79: =TRIM(Dataset!I79) -> Returned | J79: =TRIM(Dataset!J79) -> TRK79810059 | K79: =TRIM(Dataset!K79) -> 5 | L79: NO COUPON | M79: =TRIM(Dataset!M79) -> Google | N79: =VALUE(TRIM(Dataset!N79)) -> 583.18
A80: =TRIM(Dataset!A80) -> ORD200078 | B80: =Dataset!B80 -> 45510 | C80: =TRIM(Dataset!C80) -> C32029 | D80: =TRIM(Dataset!D80) -> Printer | E80: =VALUE(TRIM(Dataset!E80)) -> 4 | F80: =VALUE(TRIM(Dataset!F80)) -> 175.36 | G80: =TRIM(Dataset!G80) -> 146 Main St | H80: =TRIM(Dataset!H80) -> Debit Card | I80: =TRIM(Dataset!I80) -> Delivered | J80: =TRIM(Dataset!J80) -> TRK68535532 | K80: =TRIM(Dataset!K80) -> 4 | L80: =Dataset!L80 -> FREESHIP | M80: =TRIM(Dataset!M80) -> Instagram | N80: =VALUE(TRIM(Dataset!N80)) -> 701.44
A81: =TRIM(Dataset!A81) -> ORD200079 | B81: =Dataset!B81 -> 45726 | C81: =TRIM(Dataset!C81) -> C76700 | D81: =TRIM(Dataset!D81) -> Tablet | E81: =VALUE(TRIM(Dataset!E81)) -> 2 | F81: =VALUE(TRIM(Dataset!F81)) -> 311.91 | G81: =TRIM(Dataset!G81) -> 103 Main St | H81: =TRIM(Dataset!H81) -> Online | I81: =TRIM(Dataset!I81) -> Shipped | J81: =TRIM(Dataset!J81) -> TRK13036341 | K81: =TRIM(Dataset!K81) -> 2 | L81: NO COUPON | M81: =TRIM(Dataset!M81) -> Facebook | N81: =VALUE(TRIM(Dataset!N81)) -> 623.82
A82: =TRIM(Dataset!A82) -> ORD200080 | B82: =Dataset!B82 -> 45104 | C82: =TRIM(Dataset!C82) -> C29041 | D82: =TRIM(Dataset!D82) -> Phone | E82: =VALUE(TRIM(Dataset!E82)) -> 3 | F82: =VALUE(TRIM(Dataset!F82)) -> 589.56 | G82: =TRIM(Dataset!G82) -> 591 Main St | H82: =TRIM(Dataset!H82) -> Online | I82: =TRIM(Dataset!I82) -> Returned | J82: =TRIM(Dataset!J82) -> TRK28840655 | K82: =TRIM(Dataset!K82) -> 6 | L82: NO COUPON | M82: =TRIM(Dataset!M82) -> Facebook | N82: =VALUE(TRIM(Dataset!N82)) -> 1768.68
A83: =TRIM(Dataset!A83) -> ORD200081 | B83: =Dataset!B83 -> 45085 | C83: =TRIM(Dataset!C83) -> C29314 | D83: =TRIM(Dataset!D83) -> Monitor | E83: =VALUE(TRIM(Dataset!E83)) -> 2 | F83: =VALUE(TRIM(Dataset!F83)) -> 394.3 | G83: =TRIM(Dataset!G83) -> 496 Main St | H83: =TRIM(Dataset!H83) -> Cash | I83: =TRIM(Dataset!I83) -> Shipped | J83: =TRIM(Dataset!J83) -> TRK59876213 | K83: =TRIM(Dataset!K83) -> 6 | L83: =Dataset!L83 -> FREESHIP | M83: =TRIM(Dataset!M83) -> Email | N83: =VALUE(TRIM(Dataset!N83)) -> 788.6
A84: =TRIM(Dataset!A84) -> ORD200082 | B84: =Dataset!B84 -> 45296 | C84: =TRIM(Dataset!C84) -> C65799 | D84: =TRIM(Dataset!D84) -> Tablet | E84: =VALUE(TRIM(Dataset!E84)) -> 4 | F84: =VALUE(TRIM(Dataset!F84)) -> 565.2 | G84: =TRIM(Dataset!G84) -> 971 Main St | H84: =TRIM(Dataset!H84) -> Debit Card | I84: =TRIM(Dataset!I84) -> Shipped | J84: =TRIM(Dataset!J84) -> TRK66906607 | K84: =TRIM(Dataset!K84) -> 9 | L84: =Dataset!L84 -> SAVE10 | M84: =TRIM(Dataset!M84) -> Google | N84: =VALUE(TRIM(Dataset!N84)) -> 2260.8
A85: =TRIM(Dataset!A85) -> ORD200083 | B85: =Dataset!B85 -> 45160 | C85: =TRIM(Dataset!C85) -> C15681 | D85: =TRIM(Dataset!D85) -> Laptop | E85: =VALUE(TRIM(Dataset!E85)) -> 4 | F85: =VALUE(TRIM(Dataset!F85)) -> 540.41 | G85: =TRIM(Dataset!G85) -> 989 Main St | H85: =TRIM(Dataset!H85) -> Credit Card | I85: =TRIM(Dataset!I85) -> Cancelled | J85: =TRIM(Dataset!J85) -> TRK75112172 | K85: =TRIM(Dataset!K85) -> 6 | L85: NO COUPON | M85: =TRIM(Dataset!M85) -> Referral | N85: =VALUE(TRIM(Dataset!N85)) -> 2161.64
A86: =TRIM(Dataset!A86) -> ORD200084 | B86: =Dataset!B86 -> 45166 | C86: =TRIM(Dataset!C86) -> C64160 | D86: =TRIM(Dataset!D86) -> Monitor | E86: =VALUE(TRIM(Dataset!E86)) -> 2 | F86: =VALUE(TRIM(Dataset!F86)) -> 165.49 | G86: =TRIM(Dataset!G86) -> 967 Main St | H86: =TRIM(Dataset!H86) -> Online | I86: =TRIM(Dataset!I86) -> Shipped | J86: =TRIM(Dataset!J86) -> TRK34121529 | K86: =TRIM(Dataset!K86) -> 4 | L86: =Dataset!L86 -> WINTER15 | M86: =TRIM(Dataset!M86) -> Instagram | N86: =VALUE(TRIM(Dataset!N86)) -> 330.98
A87: =TRIM(Dataset!A87) -> ORD200085 | B87: =Dataset!B87 -> 45544 | C87: =TRIM(Dataset!C87) -> C14553 | D87: =TRIM(Dataset!D87) -> Tablet | E87: =VALUE(TRIM(Dataset!E87)) -> 3 | F87: =VALUE(TRIM(Dataset!F87)) -> 146.73 | G87: =TRIM(Dataset!G87) -> 768 Main St | H87: =TRIM(Dataset!H87) -> Cash | I87: =TRIM(Dataset!I87) -> Delivered | J87: =TRIM(Dataset!J87) -> TRK93538334 | K87: =TRIM(Dataset!K87) -> 8 | L87: =Dataset!L87 -> FREESHIP | M87: =TRIM(Dataset!M87) -> Email | N87: =VALUE(TRIM(Dataset!N87)) -> 440.19
A88: =TRIM(Dataset!A88) -> ORD200086 | B88: =Dataset!B88 -> 45462 | C88: =TRIM(Dataset!C88) -> C88205 | D88: =TRIM(Dataset!D88) -> Printer | E88: =VALUE(TRIM(Dataset!E88)) -> 5 | F88: =VALUE(TRIM(Dataset!F88)) -> 643.03 | G88: =TRIM(Dataset!G88) -> 447 Main St | H88: =TRIM(Dataset!H88) -> Online | I88: =TRIM(Dataset!I88) -> Cancelled | J88: =TRIM(Dataset!J88) -> TRK93504166 | K88: =TRIM(Dataset!K88) -> 5 | L88: =Dataset!L88 -> FREESHIP | M88: =TRIM(Dataset!M88) -> Referral | N88: =VALUE(TRIM(Dataset!N88)) -> 3215.15
A89: =TRIM(Dataset!A89) -> ORD200087 | B89: =Dataset!B89 -> 45575 | C89: =TRIM(Dataset!C89) -> C91245 | D89: =TRIM(Dataset!D89) -> Tablet | E89: =VALUE(TRIM(Dataset!E89)) -> 3 | F89: =VALUE(TRIM(Dataset!F89)) -> 225.11 | G89: =TRIM(Dataset!G89) -> 915 Main St | H89: =TRIM(Dataset!H89) -> Cash | I89: =TRIM(Dataset!I89) -> Shipped | J89: =TRIM(Dataset!J89) -> TRK46976391 | K89: =TRIM(Dataset!K89) -> 4 | L89: =Dataset!L89 -> SAVE10 | M89: =TRIM(Dataset!M89) -> Facebook | N89: =VALUE(TRIM(Dataset!N89)) -> 675.33
A90: =TRIM(Dataset!A90) -> ORD200088 | B90: =Dataset!B90 -> 45813 | C90: =TRIM(Dataset!C90) -> C75439 | D90: =TRIM(Dataset!D90) -> Desk | E90: =VALUE(TRIM(Dataset!E90)) -> 3 | F90: =VALUE(TRIM(Dataset!F90)) -> 114.81 | G90: =TRIM(Dataset!G90) -> 318 Main St | H90: =TRIM(Dataset!H90) -> Gift Card | I90: =TRIM(Dataset!I90) -> Cancelled | J90: =TRIM(Dataset!J90) -> TRK19831653 | K90: =TRIM(Dataset!K90) -> 7 | L90: NO COUPON | M90: =TRIM(Dataset!M90) -> Google | N90: =VALUE(TRIM(Dataset!N90)) -> 344.43
A91: =TRIM(Dataset!A91) -> ORD200089 | B91: =Dataset!B91 -> 45713 | C91: =TRIM(Dataset!C91) -> C17181 | D91: =TRIM(Dataset!D91) -> Printer | E91: =VALUE(TRIM(Dataset!E91)) -> 5 | F91: =VALUE(TRIM(Dataset!F91)) -> 455.33 | G91: =TRIM(Dataset!G91) -> 291 Main St | H91: =TRIM(Dataset!H91) -> Credit Card | I91: =TRIM(Dataset!I91) -> Cancelled | J91: =TRIM(Dataset!J91) -> TRK78912978 | K91: =TRIM(Dataset!K91) -> 8 | L91: =Dataset!L91 -> FREESHIP | M91: =TRIM(Dataset!M91) -> Google | N91: =VALUE(TRIM(Dataset!N91)) -> 2276.65
A92: =TRIM(Dataset!A92) -> ORD200090 | B92: =Dataset!B92 -> 45187 | C92: =TRIM(Dataset!C92) -> C36540 | D92: =TRIM(Dataset!D92) -> Chair | E92: =VALUE(TRIM(Dataset!E92)) -> 4 | F92: =VALUE(TRIM(Dataset!F92)) -> 182.08 | G92: =TRIM(Dataset!G92) -> 611 Main St | H92: =TRIM(Dataset!H92) -> Gift Card | I92: =TRIM(Dataset!I92) -> Delivered | J92: =TRIM(Dataset!J92) -> TRK35828122 | K92: =TRIM(Dataset!K92) -> 4 | L92: =Dataset!L92 -> SAVE10 | M92: =TRIM(Dataset!M92) -> Email | N92: =VALUE(TRIM(Dataset!N92)) -> 728.32
A93: =TRIM(Dataset!A93) -> ORD200091 | B93: =Dataset!B93 -> 45000 | C93: =TRIM(Dataset!C93) -> C98216 | D93: =TRIM(Dataset!D93) -> Laptop | E93: =VALUE(TRIM(Dataset!E93)) -> 5 | F93: =VALUE(TRIM(Dataset!F93)) -> 492.75 | G93: =TRIM(Dataset!G93) -> 196 Main St | H93: =TRIM(Dataset!H93) -> Cash | I93: =TRIM(Dataset!I93) -> Shipped | J93: =TRIM(Dataset!J93) -> TRK40986666 | K93: =TRIM(Dataset!K93) -> 6 | L93: =Dataset!L93 -> WINTER15 | M93: =TRIM(Dataset!M93) -> Referral | N93: =VALUE(TRIM(Dataset!N93)) -> 2463.75
A94: =TRIM(Dataset!A94) -> ORD200092 | B94: =Dataset!B94 -> 45453 | C94: =TRIM(Dataset!C94) -> C29568 | D94: =TRIM(Dataset!D94) -> Printer | E94: =VALUE(TRIM(Dataset!E94)) -> 4 | F94: =VALUE(TRIM(Dataset!F94)) -> 48.61 | G94: =TRIM(Dataset!G94) -> 203 Main St | H94: =TRIM(Dataset!H94) -> Online | I94: =TRIM(Dataset!I94) -> Shipped | J94: =TRIM(Dataset!J94) -> TRK46531075 | K94: =TRIM(Dataset!K94) -> 7 | L94: =Dataset!L94 -> FREESHIP | M94: =TRIM(Dataset!M94) -> Facebook | N94: =VALUE(TRIM(Dataset!N94)) -> 194.44
A95: =TRIM(Dataset!A95) -> ORD200093 | B95: =Dataset!B95 -> 44940 | C95: =TRIM(Dataset!C95) -> C97262 | D95: =TRIM(Dataset!D95) -> Desk | E95: =VALUE(TRIM(Dataset!E95)) -> 4 | F95: =VALUE(TRIM(Dataset!F95)) -> 431.01 | G95: =TRIM(Dataset!G95) -> 837 Main St | H95: =TRIM(Dataset!H95) -> Credit Card | I95: =TRIM(Dataset!I95) -> Returned | J95: =TRIM(Dataset!J95) -> TRK65990229 | K95: =TRIM(Dataset!K95) -> 7 | L95: NO COUPON | M95: =TRIM(Dataset!M95) -> Referral | N95: =VALUE(TRIM(Dataset!N95)) -> 1724.04
A96: =TRIM(Dataset!A96) -> ORD200094 | B96: =Dataset!B96 -> 44968 | C96: =TRIM(Dataset!C96) -> C79821 | D96: =TRIM(Dataset!D96) -> Chair | E96: =VALUE(TRIM(Dataset!E96)) -> 1 | F96: =VALUE(TRIM(Dataset!F96)) -> 531.18 | G96: =TRIM(Dataset!G96) -> 781 Main St | H96: =TRIM(Dataset!H96) -> Gift Card | I96: =TRIM(Dataset!I96) -> Returned | J96: =TRIM(Dataset!J96) -> TRK12780193 | K96: =TRIM(Dataset!K96) -> 6 | L96: =Dataset!L96 -> WINTER15 | M96: =TRIM(Dataset!M96) -> Instagram | N96: =VALUE(TRIM(Dataset!N96)) -> 531.18
A97: =TRIM(Dataset!A97) -> ORD200095 | B97: =Dataset!B97 -> 45009 | C97: =TRIM(Dataset!C97) -> C76761 | D97: =TRIM(Dataset!D97) -> Printer | E97: =VALUE(TRIM(Dataset!E97)) -> 4 | F97: =VALUE(TRIM(Dataset!F97)) -> 117.51 | G97: =TRIM(Dataset!G97) -> 839 Main St | H97: =TRIM(Dataset!H97) -> Debit Card | I97: =TRIM(Dataset!I97) -> Returned | J97: =TRIM(Dataset!J97) -> TRK60179774 | K97: =TRIM(Dataset!K97) -> 7 | L97: NO COUPON | M97: =TRIM(Dataset!M97) -> Referral | N97: =VALUE(TRIM(Dataset!N97)) -> 470.04
A98: =TRIM(Dataset!A98) -> ORD200096 | B98: =Dataset!B98 -> 45444 | C98: =TRIM(Dataset!C98) -> C93007 | D98: =TRIM(Dataset!D98) -> Phone | E98: =VALUE(TRIM(Dataset!E98)) -> 2 | F98: =VALUE(TRIM(Dataset!F98)) -> 232.83 | G98: =TRIM(Dataset!G98) -> 103 Main St | H98: =TRIM(Dataset!H98) -> Gift Card | I98: =TRIM(Dataset!I98) -> Delivered | J98: =TRIM(Dataset!J98) -> TRK85696091 | K98: =TRIM(Dataset!K98) -> 7 | L98: NO COUPON | M98: =TRIM(Dataset!M98) -> Instagram | N98: =VALUE(TRIM(Dataset!N98)) -> 465.66
A99: =TRIM(Dataset!A99) -> ORD200097 | B99: =Dataset!B99 -> 45678 | C99: =TRIM(Dataset!C99) -> C15624 | D99: =TRIM(Dataset!D99) -> Tablet | E99: =VALUE(TRIM(Dataset!E99)) -> 5 | F99: =VALUE(TRIM(Dataset!F99)) -> 619.52 | G99: =TRIM(Dataset!G99) -> 922 Main St | H99: =TRIM(Dataset!H99) -> Debit Card | I99: =TRIM(Dataset!I99) -> Pending | J99: =TRIM(Dataset!J99) -> TRK40621141 | K99: =TRIM(Dataset!K99) -> 9 | L99: NO COUPON | M99: =TRIM(Dataset!M99) -> Email | N99: =VALUE(TRIM(Dataset!N99)) -> 3097.6
A100: =TRIM(Dataset!A100) -> ORD200098 | B100: =Dataset!B100 -> 44940 | C100: =TRIM(Dataset!C100) -> C70921 | D100: =TRIM(Dataset!D100) -> Printer | E100: =VALUE(TRIM(Dataset!E100)) -> 2 | F100: =VALUE(TRIM(Dataset!F100)) -> 228.54 | G100: =TRIM(Dataset!G100) -> 533 Main St | H100: =TRIM(Dataset!H100) -> Debit Card | I100: =TRIM(Dataset!I100) -> Pending | J100: =TRIM(Dataset!J100) -> TRK54983109 | K100: =TRIM(Dataset!K100) -> 3 | L100: NO COUPON | M100: =TRIM(Dataset!M100) -> Email | N100: =VALUE(TRIM(Dataset!N100)) -> 457.08
...

Sheet Analysis
A1: Most Selling Product | D1: Revenue by Product | G1: Most Frequent Orderstatus | J1: Average Items per cart
A2: Product | B2: Sum of Quantity | D2: Product | E2: Sum of TotalPrice | G2: OrderStatus | H2: Total Orders | J2: Product | K2: Average of Quantity
A3: Phone | B3: 411 | D3: Chair | E3: 195620.11 | G3: Delivered | H3: 231 | J3: Chair | K3: 3.1573034
A4: Monitor | B4: 480 | D4: Printer | E4: 195612.61 | G4: Shipped | H4: 235 | J4: Desk | K4: 2.9882353
A5: Tablet | B5: 497 | D5: Laptop | E5: 192126.56 | G5: Pending | H5: 237 | J5: Laptop | K5: 3.0924855
A6: Desk | B6: 508 | D6: Tablet | E6: 186568.95 | G6: Returned | H6: 247 | J6: Monitor | K6: 2.9447853
A7: Laptop | B7: 535 | D7: Monitor | E7: 175651.41 | G7: Cancelled | H7: 250 | J7: Phone | K7: 2.6346154
A8: Printer | B8: 542 | D8: Desk | E8: 167459.93 | G8: Grand Total | H8: 1200 | J8: Printer | K8: 2.9944751
A9: Chair | B9: 562 | D9: Phone | E9: 151722.39 | J9: Tablet | K9: 2.7765363
A10: Grand Total | B10: 3535 | D10: Grand Total | E10: 1264762 | J10: Grand Total | K10: 2.9458333
A12: Most used payment Method | D12: Top Referral Source | G12: Sales Overtime | J12: Top Referral Source
A13: Payment Method | B13: Total Orders | D13: CouponCode | E13: Total Orders | G13: CouponCode | H13: Sum of Quantity | I13: Sum of TotalPrice | J13: CouponCode | K13: Total Orders
A14: Gift Card | B14: 230 | D14: FREESHIP | E14: 313 | G14: 2023 | H14: 1524 | I14: 552643.24 | J14: FREESHIP | K14: 0.26083333
A15: Debit Card | B15: 232 | D15: NO COUPON | E15: 309 | G15: 2024 | H15: 1351 | I15: 480235.87 | J15: NO COUPON | K15: 0.2575
A16: Credit Card | B16: 234 | D16: WINTER15 | E16: 292 | G16: 2025 | H16: 660 | I16: 231882.85 | J16: WINTER15 | K16: 0.24333333
A17: Cash | B17: 246 | D17: SAVE10 | E17: 286 | G17: Grand Total | H17: 3535 | I17: 1264762 | J17: SAVE10 | K17: 0.23833333
A18: Online | B18: 258 | D18: Grand Total | E18: 1200 | J18: Grand Total | K18: 1
A19: Grand Total | B19: 1200
A21: Revenue | B21: Quantity | D21: Average of TotalPrice
A22: 1264762 | B22: 3535 | D22: 1053.9683

Sheet Dashboard

Sheet Outliner 
A2: Order with unsual high price | D2: Product with unsual high price | G2: Orders with Unsual quantity
A3: OrderID | B3: Cost of orders | D3: Product | E3: Average of UnitPrice | G3: OrderID | H3: Sum of Quantity
A4: ORD200789 | B4: 3456.4 | D4: Phone | E4: 375.21756 | G4: ORD201051 | H4: 5
A5: ORD201122 | B5: 3390.95 | D5: Tablet | E5: 367.67911 | G5: ORD201006 | H5: 5
A6: ORD200632 | B6: 3390.8 | D6: Monitor | E6: 358.66362 | G6: ORD201100 | H6: 5
A7: ORD200469 | B7: 3384.9 | D7: Laptop | E7: 357.70705 | G7: ORD200907 | H7: 5
A8: ORD200328 | B8: 3370.2 | D8: Chair | E8: 355.66028 | G8: ORD201031 | H8: 5
A9: ORD200107 | B9: 3353.75 | D9: Printer | E9: 351.71492 | G9: ORD200911 | H9: 5
A10: ORD200326 | B10: 3352.4 | D10: Desk | E10: 329.60812 | G10: ORD201079 | H10: 5
A11: ORD201065 | B11: 3334 | D11: Grand Total | E11: 356.41275 | G11: ORD200913 | H11: 5
A12: ORD201031 | B12: 3322.55 | G12: ORD201146 | H12: 5
A13: ORD200463 | B13: 3313.9 | G13: ORD200916 | H13: 5
A14: ORD200361 | B14: 3299.25 | G14: ORD201016 | H14: 5
A15: ORD200367 | B15: 3293.85 | G15: ORD200917 | H15: 5
A16: ORD200837 | B16: 3277.75 | G16: ORD200900 | H16: 5
A17: ORD200527 | B17: 3267.35 | G17: ORD200918 | H17: 5
A18: ORD200768 | B18: 3267.3 | G18: ORD201062 | H18: 5
A19: ORD200889 | B19: 3253.6 | G19: ORD200924 | H19: 5
A20: ORD200540 | B20: 3243.25 | G20: ORD201092 | H20: 5
A21: ORD200802 | B21: 3223.2 | G21: ORD200925 | H21: 5
A22: ORD200957 | B22: 3219.45 | G22: ORD201126 | H22: 5
A23: ORD200086 | B23: 3215.15 | G23: ORD200941 | H23: 5
... A1204: Grand Total | B1204: 1264762 | G1204: Grand Total | H1204: 3535
